Workbook

Sheet Plan
A1: Project 3 Kit: Retail Sales & Profit Dashboard
A2: Power Query merge, KPIs, ABC product analysis, RFM customer analysis, pivot tables and a one-page dashboard
A4: Block | B4: Time | C4: Sheet | D4: Goal
A5: 1. Power Query merge and clean | B5: 60 min | C5: 1 Clean Check, CSV files | D5: Combine 12 monthly CSV files, fix the four planted issues, reconcile counts to Sales Data
A6: 2. KPIs and formulas | B6: 40 min | C6: Sales Data, 2 KPI Tasks | D6: SUMIFS, COUNTIFS and SUMPRODUCT: sales, profit, margin, order value, returns, loss-making orders
A7: 3. Product ABC analysis | B7: 45 min | C7: Products, 3 ABC Tasks | D7: Find the few products that make most of the sales, the loss-makers and the dead stock
A8: 4. Customer RFM analysis | B8: 45 min | C8: Customers, 4 RFM Tasks | D8: Score every customer on recency, frequency and spend, then segment them
A9: 5. Pivot tables and dashboard | B9: 90 min | C9: 5 Dashboard Tasks | D9: Build the pivots yourself, then a one-page dashboard with slicers and a timeline
A10: 6. Insights and README | B10: 45 min | C10: 6 Insights | D10: Write five findings with numbers and recommendations, then package the repo
A11: 7. Review | B11: 20 min | C11: Answer Key | D11: Check your answers, log every mistake below, redo those tasks
A13: Data | B13: Practice data made up for this kit: 1,200 orders (one product per order), 40 products, 220 customers, Jan to Dec 2025, in ₹.
A14: Yellow cells | B14: Yellow means you type or fill down. Everything else is given. The Answer Key marks your yellow answers automatically.
A15: Your score | B15: ='Answer Key'!B3 -> 44 out of 44
A16: Versions | B16: Power Query, slicers and timelines need Excel 2016 or later (Microsoft 365 recommended). The Answer Key uses INDEX and MATCH, so it works in any version.
A18: Deliverables checklist
A19: Deliverable | B19: What it contains | C19: Where it goes | D19: Done? (Y/N)
A20: README.md | B20: Business problem, data, method, top 3 findings with numbers, dashboard screenshot | C20: Repo folder 03-retail-sales-profit-dashboard | D20: Y
A21: Excel workbook | B21: Power Query steps, KPI sheet, ABC, RFM, dashboard | C21: Same folder | D21: Y
A22: Dashboard screenshot | B22: One page: four KPI cards, three charts, two slicers, a timeline | C22: Top of the README | D22: Y
A23: One-page PDF summary | B23: Five findings and recommendations, like a client report | C23: Same folder, and a sample to send to clients | D23: Y
A24: 60-second screen recording | B24: Refresh, slicers and KPI cards in use | C24: Link in the README | D24: N
A26: Mistake log
A27: Question | B27: What went wrong | C27: Correct formula / idea | D27: Redone? (Y/N)
A28: Ex. KPI 3 | B28: Divided Profit by Cost instead of Sales | C28: =SUM(R2:R1201)/SUM(P2:P1201) | D28: Y

Sheet 1 Clean Check
A1: 1. Power Query: merge and clean
A2: Files: Retail_Sales_Monthly_CSVs.zip (Sales_2025-01.csv to Sales_2025-12.csv). Type your answers in the yellow cells.
A3: Your cleaned table should match the Sales Data sheet exactly. That sheet is the finished, clean version.
A4: No. | B4: Task | C4: Your answer | D4: Done? (Y/N)
A5: 1 | B5: Load the 12 CSV files with Data > Get Data > From File > From Folder and combine them. How many data rows are in the combined table before any cleaning? | C5: 1210 | D5: Y
A6: 2 | B6: Remove exact duplicate rows. How many rows did you remove? | C6: =C5-C7 -> 10 | D6: Y
A7: 3 | B7: How many rows are left after cleaning? | C7: =COUNTA('Sales Data'!$A$2:$A$1201) -> 1200 | D7: Y
A8: 4 | B8: What is the total of the Sales (₹) column after cleaning? | C8: =SUM('Sales Data'!$P$2:$P$1201) -> 5426671 | D8: Y
A9: 5 | B9: After trimming spaces and capitalising each word, how many different Customer Name values are there? | C9: =ROUND(SUMPRODUCT(1/COUNTIF('Sales Data'!$E$2:$E$1201,'Sales Data'!$E$2:$E$1201)),0) -> 220 | D9: Y
A10: 6 | B10: After fixing capitalisation, how many different Region values are there? | C10: =ROUND(SUMPRODUCT(1/COUNTIF('Sales Data'!$G$2:$G$1201,'Sales Data'!$G$2:$G$1201)),0) -> 4 | D10: Y
A11: 7 | B11: After standardising the Returned column to Y / N, how many rows have Returned = Y? | C11: =COUNTIF('Sales Data'!$S$2:$S$1201,"Y") -> 48 | D11: Y
A12: 8 | B12: Load the result as a connection plus a table named Sales_Clean, with the query named Sales_Clean. Mark Y when done. | C12: Do in Excel: paste Sales_Clean.m (see Power Query Steps sheet) | D12: N
A13: 9 | B13: Refresh test: change one Sales (₹) value in one CSV file, click Data > Refresh All, and confirm the total moved by the same amount. Mark Y when done. | C13: Do in Excel after loading the query | D13: N
A16: Planted issues (reference)
A17: No. | B17: Issue and where it appears | C17: Power Query step
A18: 1 | B18: Customer Name has extra spaces or all capitals on about 3% of rows, in every file. | C18: Transform > Format > Trim, then Capitalize Each Word
A19: 2 | B19: Region is written in lower case or all capitals on about 3% of rows, in every file. | C19: Transform > Format > Capitalize Each Word
A20: 3 | B20: Returned says Yes / No in the September to December files but Y / N in the others. | C20: Transform > Replace Values (Yes to Y, No to N)
A21: 4 | B21: Some rows appear twice inside a monthly file. | C21: Home > Remove Rows > Remove Duplicates (select all columns)

Sheet Power Query Steps
A1: Power Query steps for the Sales_Clean query
A2: Full M script: power_query/Sales_Clean.m in the repo. The same logic is reproduced and checked by scripts/clean_and_verify.py (1,210 raw rows -> 1,200 clean rows, ₹54,26,671 sales).
A4: Step | B4: Excel ribbon action | C4: Power Query step name | D4: Rows after step | E4: Why
A5: 1 | B5: Data > Get Data > From File > From Folder; Combine & Transform | C5: Source / Combined | D5: 1210 | E5: Stack the 12 monthly files into one table
A6: 2 | B6: Home > Use First Row as Headers | C6: Promoted Headers | D6: 1210 | E6: Each CSV has its own header row
A7: 3 | B7: Transform > Format > Trim, then Capitalize Each Word on Customer Name | C7: Cleaned Names | D7: 1210 | E7: Fixes extra spaces and ALL CAPS on ~3% of rows
A8: 4 | B8: Transform > Format > Trim, then Capitalize Each Word on Region | C8: Cleaned Region | D8: 1210 | E8: Fixes north / WEST style entries (11 distinct values -> 4)
A9: 5 | B9: Transform > Replace Values on Returned (Yes to Y, No to N) | C9: Standardised Returned | D9: 1210 | E9: Sep-Dec files use Yes / No
A10: 6 | B10: Transform > Data Type: dates, whole numbers, decimals | C10: Changed Type | D10: 1210 | E10: Correct types so SUM and date math work
A11: 7 | B11: Home > Remove Rows > Remove Duplicates (all columns selected) | C11: Removed Duplicates | D11: 1200 | E11: 10 exact duplicate rows planted inside monthly files
A12: 8 | B12: Close & Load To... > Connection + Table, query named Sales_Clean | C12: Sales_Clean | D12: 1200 | E12: Feeds the KPI, ABC, RFM and dashboard sheets
A15: Reconciliation (live formulas on Sales Data)
B16: Check | C16: Value
B17: Rows after cleaning | C17: =COUNTA('Sales Data'!$A$2:$A$1201) -> 1200
B18: Duplicate Order IDs left | C18: =COUNTA('Sales Data'!$A$2:$A$1201)-SUMPRODUCT(1/COUNTIF('Sales Data'!$A$2:$A$1201,'Sales Data'!$A$2:$A$1201)) -> 0
B19: Total Sales (₹) | C19: =SUM('Sales Data'!$P$2:$P$1201) -> 5426671
B20: Distinct Regions | C20: =ROUND(SUMPRODUCT(1/COUNTIF('Sales Data'!$G$2:$G$1201,'Sales Data'!$G$2:$G$1201)),0) -> 4
B21: Returned = Y | C21: =COUNTIF('Sales Data'!$S$2:$S$1201,"Y") -> 48

Sheet Sales Data
A1: Order ID | B1: Order Date | C1: Ship Date | D1: Customer ID | E1: Customer Name | F1: Segment | G1: Region | H1: City | I1: Category | J1: Sub-Category | K1: Product ID | L1: Product Name | M1: Qty | N1: Unit Price (₹) | O1: Discount | P1: Sales (₹) | Q1: Cost (₹) | R1: Profit (₹) | S1: Returned | T1: Discount Band
A2: ORD-2001 | B2: 45658 | C2: 45659 | D2: C218 | E2: Rajat Mehta | F2: Consumer | G2: West | H2: Pune | I2: Apparel | J2: Bottomwear | K2: P006 | L2: Denim Jeans | M2: 2 | N2: 1999 | O2: 0.3 | P2: 2799 | Q2: 2100 | R2: 699 | S2: N | T2: =IF(O2=0,"No discount",IF(O2<=0.2,"Up to 20%","Above 20%")) -> Above 20%
A3: ORD-2002 | B3: 45658 | C3: 45659 | D3: C024 | E3: Rajat Bhatt | F3: Consumer | G3: South | H3: Chennai | I3: Home | J3: Decor | K3: P025 | L3: Cushion Cover Set | M3: 1 | N3: 699 | O3: 0.05 | P3: 664 | Q3: 320 | R3: 344 | S3: N | T3: =IF(O3=0,"No discount",IF(O3<=0.2,"Up to 20%","Above 20%")) -> Up to 20%
A4: ORD-2003 | B4: 45658 | C4: 45660 | D4: C172 | E4: Pankaj Kapoor | F4: Home Office | G4: South | H4: Bengaluru | I4: Home | J4: Decor | K4: P010 | L4: Table Lamp | M4: 1 | N4: 999 | O4: 0.05 | P4: 949 | Q4: 520 | R4: 429 | S4: N | T4: =IF(O4=0,"No discount",IF(O4<=0.2,"Up to 20%","Above 20%")) -> Up to 20%
A5: ORD-2004 | B5: 45660 | C5: 45662 | D5: C148 | E5: Divya Jain | F5: Home Office | G5: West | H5: Pune | I5: Apparel | J5: Footwear | K5: P020 | L5: Running Shoes | M5: 1 | N5: 3299 | O5: 0.4 | P5: 1979 | Q5: 1900 | R5: 79 | S5: N | T5: =IF(O5=0,"No discount",IF(O5<=0.2,"Up to 20%","Above 20%")) -> Above 20%
A6: ORD-2005 | B6: 45660 | C6: 45664 | D6: C065 | E6: Aditya Shah | F6: Consumer | G6: South | H6: Hyderabad | I6: Furniture | J6: Seating | K6: P033 | L6: Office Chair | M6: 1 | N6: 8999 | O6: 0.3 | P6: 6299 | Q6: 6800 | R6: -501 | S6: N | T6: =IF(O6=0,"No discount",IF(O6<=0.2,"Up to 20%","Above 20%")) -> Above 20%
A7: ORD-2006 | B7: 45660 | C7: 45666 | D7: C212 | E7: Karan Das | F7: Home Office | G7: South | H7: Hyderabad | I7: Beauty | J7: Makeup | K7: P027 | L7: Lip Balm Set | M7: 4 | N7: 399 | O7: 0 | P7: 1596 | Q7: 640 | R7: 956 | S7: N | T7: =IF(O7=0,"No discount",IF(O7<=0.2,"Up to 20%","Above 20%")) -> No discount
A8: ORD-2007 | B8: 45661 | C8: 45664 | D8: C200 | E8: Aditya Joshi | F8: Consumer | G8: North | H8: Delhi | I8: Electronics | J8: Accessories | K8: P017 | L8: Mechanical Keyboard | M8: 1 | N8: 3499 | O8: 0.05 | P8: 3324 | Q8: 2200 | R8: 1124 | S8: N | T8: =IF(O8=0,"No discount",IF(O8<=0.2,"Up to 20%","Above 20%")) -> Up to 20%
A9: ORD-2008 | B9: 45662 | C9: 45668 | D9: C200 | E9: Aditya Joshi | F9: Consumer | G9: North | H9: Delhi | I9: Furniture | J9: Storage | K9: P035 | L9: Bookshelf | M9: 1 | N9: 5999 | O9: 0.3 | P9: 4199 | Q9: 4600 | R9: -401 | S9: N | T9: =IF(O9=0,"No discount",IF(O9<=0.2,"Up to 20%","Above 20%")) -> Above 20%
A10: ORD-2009 | B10: 45662 | C10: 45665 | D10: C034 | E10: Ramesh Saxena | F10: Corporate | G10: North | H10: Delhi | I10: Electronics | J10: Accessories | K10: P017 | L10: Mechanical Keyboard | M10: 1 | N10: 3499 | O10: 0.05 | P10: 3324 | Q10: 2200 | R10: 1124 | S10: N | T10: =IF(O10=0,"No discount",IF(O10<=0.2,"Up to 20%","Above 20%")) -> Up to 20%
A11: ORD-2010 | B11: 45663 | C11: 45665 | D11: C163 | E11: Kavya Das | F11: Corporate | G11: West | H11: Pune | I11: Beauty | J11: Skincare | K11: P011 | L11: Face Serum | M11: 3 | N11: 899 | O11: 0.15 | P11: 2292 | Q11: 1140 | R11: 1152 | S11: N | T11: =IF(O11=0,"No discount",IF(O11<=0.2,"Up to 20%","Above 20%")) -> Up to 20%
A12: ORD-2011 | B12: 45663 | C12: 45667 | D12: C137 | E12: Priya Verma | F12: Consumer | G12: South | H12: Bengaluru | I12: Furniture | J12: Storage | K12: P035 | L12: Bookshelf | M12: 1 | N12: 5999 | O12: 0.1 | P12: 5399 | Q12: 4600 | R12: 799 | S12: N | T12: =IF(O12=0,"No discount",IF(O12<=0.2,"Up to 20%","Above 20%")) -> Up to 20%
A13: ORD-2012 | B13: 45664 | C13: 45667 | D13: C135 | E13: Sneha Bhatt | F13: Corporate | G13: South | H13: Hyderabad | I13: Electronics | J13: Audio | K13: P018 | L13: Noise-Cancelling Headphones | M13: 1 | N13: 7999 | O13: 0.05 | P13: 7599 | Q13: 5600 | R13: 1999 | S13: N | T13: =IF(O13=0,"No discount",IF(O13<=0.2,"Up to 20%","Above 20%")) -> Up to 20%
... A1201: ORD-3200 | B1201: 46022 | C1201: 46023 | D1201: C188 | E1201: Zoya Desai | F1201: Home Office | G1201: North | H1201: Delhi | I1201: Apparel | J1201: Bottomwear | K1201: P006 | L1201: Denim Jeans | M1201: 1 | N1201: 1999 | O1201: 0.3 | P1201: 1399 | Q1201: 1050 | R1201: 349 | S1201: N | T1201: =IF(O1201=0,"No discount",IF(O1201<=0.2,"Up to 20%","Above 20%")) -> Above 20%

Sheet 2 KPI Tasks
A1: 2. KPIs and formulas
A2: Use the Sales Data sheet and formulas such as SUMIFS, COUNTIFS and SUMPRODUCT. Type your answers in the yellow cells.
A4: No. | B4: Task | C4: Your answer | D4: Done? (Y/N)
A5: 1 | B5: What is the total Sales (₹)? | C5: =SUM('Sales Data'!$P$2:$P$1201) -> 5426671 | D5: Y
A6: 2 | B6: What is the total Profit (₹)? | C6: =SUM('Sales Data'!$R$2:$R$1201) -> 1212441 | D6: Y
A7: 3 | B7: What is the overall profit margin (Profit divided by Sales)? Enter it as a percentage. | C7: =C6/C5 -> 0.22342261 | D7: Y
A8: 4 | B8: How many orders are there? (Each row is one order.) | C8: =COUNTA('Sales Data'!$A$2:$A$1201) -> 1200 | D8: Y
A9: 5 | B9: What is the average order value (₹), Sales divided by the number of orders? | C9: =C5/C8 -> 4522.2258 | D9: Y
A10: 6 | B10: What is the return rate, orders with Returned = Y divided by all orders? Enter it as a percentage. | C10: =COUNTIF('Sales Data'!$S$2:$S$1201,"Y")/C8 -> 0.04 | D10: Y
A11: 7 | B11: Which month has the highest Sales? Enter the month name. | C11: =INDEX(Pivots!$B$24:$B$35,MATCH(MAX(Pivots!$D$24:$D$35),Pivots!$D$24:$D$35,0)) -> November | D11: Y
A12: 8 | B12: By what percentage did Sales change from November to December? (December minus November, divided by November.) | C12: =(Pivots!$D$35-Pivots!$D$34)/Pivots!$D$34 -> -0.31373624 | D12: Y
A13: 9 | B13: What are the total Sales (₹) of the West region on orders with a discount of 20% or more? | C13: =SUMIFS('Sales Data'!$P$2:$P$1201,'Sales Data'!$G$2:$G$1201,"West",'Sales Data'!$O$2:$O$1201,">=0.2") -> 698690 | D13: Y
A14: 10 | B14: How many orders lost money (Profit below zero)? | C14: =COUNTIF('Sales Data'!$R$2:$R$1201,"<0") -> 92 | D14: Y
A15: 11 | B15: What is the total loss (₹) on those orders? Enter it as a positive number. | C15: =-SUMIF('Sales Data'!$R$2:$R$1201,"<0") -> 85926 | D15: Y
A16: 12 | B16: What is the average number of days from order to ship? (2 decimal places) | C16: =ROUND(SUMPRODUCT('Sales Data'!$C$2:$C$1201-'Sales Data'!$B$2:$B$1201)/COUNTA('Sales Data'!$A$2:$A$1201),2) -> 4 | D16: Y

Sheet Products
A1: Products: ABC analysis
A2: Fill down each yellow column from the first row. Read the Sales Data sheet; do not type numbers in.
A4: Product ID | B4: Product Name | C4: Category | D4: Sub-Category | E4: Unit Price (₹) | F4: Unit Cost (₹) | H4: Units Sold | I4: Sales (₹) | J4: Profit (₹) | K4: Profit Margin | L4: Sales Share | M4: Cumulative Share | N4: ABC Class
A5: P001 | B5: Wireless Earbuds | C5: Electronics | D5: Audio | E5: 2499 | F5: 1500 | H5: =SUMIFS('Sales Data'!$M$2:$M$1201,'Sales Data'!$K$2:$K$1201,A5) -> 10 | I5: =SUMIFS('Sales Data'!$P$2:$P$1201,'Sales Data'!$K$2:$K$1201,A5) -> 24240 | J5: =SUMIFS('Sales Data'!$R$2:$R$1201,'Sales Data'!$K$2:$K$1201,A5) -> 9240 | K5: =IF(I5=0,0,J5/I5) -> 0.38118812 | L5: =I5/SUM($I$5:$I$44) -> 0.0044668269 | M5: =SUMIF($I$5:$I$44,">="&I5)/SUM($I$5:$I$44) -> 0.97916421 | N5: =IF(M5<=0.8,"A",IF(M5<=0.95,"B",IF(M5<=1,"C","C"))) -> C
A6: P002 | B6: Smart Watch | C6: Electronics | D6: Wearables | E6: 5999 | F6: 4300 | H6: =SUMIFS('Sales Data'!$M$2:$M$1201,'Sales Data'!$K$2:$K$1201,A6) -> 37 | I6: =SUMIFS('Sales Data'!$P$2:$P$1201,'Sales Data'!$K$2:$K$1201,A6) -> 208164 | J6: =SUMIFS('Sales Data'!$R$2:$R$1201,'Sales Data'!$K$2:$K$1201,A6) -> 49064 | K6: =IF(I6=0,0,J6/I6) -> 0.23569878 | L6: =I6/SUM($I$5:$I$44) -> 0.038359429 | M6: =SUMIF($I$5:$I$44,">="&I6)/SUM($I$5:$I$44) -> 0.66130506 | N6: =IF(M6<=0.8,"A",IF(M6<=0.95,"B",IF(M6<=1,"C","C"))) -> A
A7: P003 | B7: Power Bank | C7: Electronics | D7: Accessories | E7: 1499 | F7: 900 | H7: =SUMIFS('Sales Data'!$M$2:$M$1201,'Sales Data'!$K$2:$K$1201,A7) -> 23 | I7: =SUMIFS('Sales Data'!$P$2:$P$1201,'Sales Data'!$K$2:$K$1201,A7) -> 31852 | J7: =SUMIFS('Sales Data'!$R$2:$R$1201,'Sales Data'!$K$2:$K$1201,A7) -> 11152 | K7: =IF(I7=0,0,J7/I7) -> 0.3501193 | L7: =I7/SUM($I$5:$I$44) -> 0.0058695285 | M7: =SUMIF($I$5:$I$44,">="&I7)/SUM($I$5:$I$44) -> 0.96475906 | N7: =IF(M7<=0.8,"A",IF(M7<=0.95,"B",IF(M7<=1,"C","C"))) -> C
A8: P004 | B8: Bluetooth Speaker | C8: Electronics | D8: Audio | E8: 3299 | F8: 2100 | H8: =SUMIFS('Sales Data'!$M$2:$M$1201,'Sales Data'!$K$2:$K$1201,A8) -> 20 | I8: =SUMIFS('Sales Data'!$P$2:$P$1201,'Sales Data'!$K$2:$K$1201,A8) -> 63670 | J8: =SUMIFS('Sales Data'!$R$2:$R$1201,'Sales Data'!$K$2:$K$1201,A8) -> 21670 | K8: =IF(I8=0,0,J8/I8) -> 0.34034867 | L8: =I8/SUM($I$5:$I$44) -> 0.011732792 | M8: =SUMIF($I$5:$I$44,">="&I8)/SUM($I$5:$I$44) -> 0.90846635 | N8: =IF(M8<=0.8,"A",IF(M8<=0.95,"B",IF(M8<=1,"C","C"))) -> B
A9: P005 | B9: Cotton T-Shirt | C9: Apparel | D9: Topwear | E9: 799 | F9: 380 | H9: =SUMIFS('Sales Data'!$M$2:$M$1201,'Sales Data'!$K$2:$K$1201,A9) -> 13 | I9: =SUMIFS('Sales Data'!$P$2:$P$1201,'Sales Data'!$K$2:$K$1201,A9) -> 7830 | J9: =SUMIFS('Sales Data'!$R$2:$R$1201,'Sales Data'!$K$2:$K$1201,A9) -> 2890 | K9: =IF(I9=0,0,J9/I9) -> 0.36909323 | L9: =I9/SUM($I$5:$I$44) -> 0.0014428735 | M9: =SUMIF($I$5:$I$44,">="&I9)/SUM($I$5:$I$44) -> 0.99968544 | N9: =IF(M9<=0.8,"A",IF(M9<=0.95,"B",IF(M9<=1,"C","C"))) -> C
A10: P006 | B10: Denim Jeans | C10: Apparel | D10: Bottomwear | E10: 1999 | F10: 1050 | H10: =SUMIFS('Sales Data'!$M$2:$M$1201,'Sales Data'!$K$2:$K$1201,A10) -> 85 | I10: =SUMIFS('Sales Data'!$P$2:$P$1201,'Sales Data'!$K$2:$K$1201,A10) -> 131131 | J10: =SUMIFS('Sales Data'!$R$2:$R$1201,'Sales Data'!$K$2:$K$1201,A10) -> 41881 | K10: =IF(I10=0,0,J10/I10) -> 0.31938291 | L10: =I10/SUM($I$5:$I$44) -> 0.02416417 | M10: =SUMIF($I$5:$I$44,">="&I10)/SUM($I$5:$I$44) -> 0.7924713 | N10: =IF(M10<=0.8,"A",IF(M10<=0.95,"B",IF(M10<=1,"C","C"))) -> A
A11: P007 | B11: Hoodie | C11: Apparel | D11: Topwear | E11: 1799 | F11: 950 | H11: =SUMIFS('Sales Data'!$M$2:$M$1201,'Sales Data'!$K$2:$K$1201,A11) -> 36 | I11: =SUMIFS('Sales Data'!$P$2:$P$1201,'Sales Data'!$K$2:$K$1201,A11) -> 53429 | J11: =SUMIFS('Sales Data'!$R$2:$R$1201,'Sales Data'!$K$2:$K$1201,A11) -> 19229 | K11: =IF(I11=0,0,J11/I11) -> 0.35989818 | L11: =I11/SUM($I$5:$I$44) -> 0.009845631 | M11: =SUMIF($I$5:$I$44,">="&I11)/SUM($I$5:$I$44) -> 0.92878765 | N11: =IF(M11<=0.8,"A",IF(M11<=0.95,"B",IF(M11<=1,"C","C"))) -> B
A12: P008 | B12: Cotton Bedsheet | C12: Home | D12: Bedding | E12: 1299 | F12: 700 | H12: =SUMIFS('Sales Data'!$M$2:$M$1201,'Sales Data'!$K$2:$K$1201,A12) -> 64 | I12: =SUMIFS('Sales Data'!$P$2:$P$1201,'Sales Data'!$K$2:$K$1201,A12) -> 75598 | J12: =SUMIFS('Sales Data'!$R$2:$R$1201,'Sales Data'!$K$2:$K$1201,A12) -> 30798 | K12: =IF(I12=0,0,J12/I12) -> 0.40739173 | L12: =I12/SUM($I$5:$I$44) -> 0.013930824 | M12: =SUMIF($I$5:$I$44,">="&I12)/SUM($I$5:$I$44) -> 0.89673356 | N12: =IF(M12<=0.8,"A",IF(M12<=0.95,"B",IF(M12<=1,"C","C"))) -> B
A13: P009 | B13: Coffee Maker | C13: Home | D13: Kitchen | E13: 2999 | F13: 2000 | H13: =SUMIFS('Sales Data'!$M$2:$M$1201,'Sales Data'!$K$2:$K$1201,A13) -> 105 | I13: =SUMIFS('Sales Data'!$P$2:$P$1201,'Sales Data'!$K$2:$K$1201,A13) -> 287750 | J13: =SUMIFS('Sales Data'!$R$2:$R$1201,'Sales Data'!$K$2:$K$1201,A13) -> 77750 | K13: =IF(I13=0,0,J13/I13) -> 0.27019983 | L13: =I13/SUM($I$5:$I$44) -> 0.053025142 | M13: =SUMIF($I$5:$I$44,">="&I13)/SUM($I$5:$I$44) -> 0.57233007 | N13: =IF(M13<=0.8,"A",IF(M13<=0.95,"B",IF(M13<=1,"C","C"))) -> A
A14: P010 | B14: Table Lamp | C14: Home | D14: Decor | E14: 999 | F14: 520 | H14: =SUMIFS('Sales Data'!$M$2:$M$1201,'Sales Data'!$K$2:$K$1201,A14) -> 81 | I14: =SUMIFS('Sales Data'!$P$2:$P$1201,'Sales Data'!$K$2:$K$1201,A14) -> 75622 | J14: =SUMIFS('Sales Data'!$R$2:$R$1201,'Sales Data'!$K$2:$K$1201,A14) -> 33502 | K14: =IF(I14=0,0,J14/I14) -> 0.44301923 | L14: =I14/SUM($I$5:$I$44) -> 0.013935247 | M14: =SUMIF($I$5:$I$44,">="&I14)/SUM($I$5:$I$44) -> 0.88280273 | N14: =IF(M14<=0.8,"A",IF(M14<=0.95,"B",IF(M14<=1,"C","C"))) -> B
A15: P011 | B15: Face Serum | C15: Beauty | D15: Skincare | E15: 899 | F15: 380 | H15: =SUMIFS('Sales Data'!$M$2:$M$1201,'Sales Data'!$K$2:$K$1201,A15) -> 63 | I15: =SUMIFS('Sales Data'!$P$2:$P$1201,'Sales Data'!$K$2:$K$1201,A15) -> 49487 | J15: =SUMIFS('Sales Data'!$R$2:$R$1201,'Sales Data'!$K$2:$K$1201,A15) -> 25547 | K15: =IF(I15=0,0,J15/I15) -> 0.51623659 | L15: =I15/SUM($I$5:$I$44) -> 0.0091192188 | M15: =SUMIF($I$5:$I$44,">="&I15)/SUM($I$5:$I$44) -> 0.93790687 | N15: =IF(M15<=0.8,"A",IF(M15<=0.95,"B",IF(M15<=1,"C","C"))) -> B
A16: P012 | B16: Perfume | C16: Beauty | D16: Fragrance | E16: 1599 | F16: 750 | H16: =SUMIFS('Sales Data'!$M$2:$M$1201,'Sales Data'!$K$2:$K$1201,A16) -> 92 | I16: =SUMIFS('Sales Data'!$P$2:$P$1201,'Sales Data'!$K$2:$K$1201,A16) -> 129437 | J16: =SUMIFS('Sales Data'!$R$2:$R$1201,'Sales Data'!$K$2:$K$1201,A16) -> 60437 | K16: =IF(I16=0,0,J16/I16) -> 0.46692213 | L16: =I16/SUM($I$5:$I$44) -> 0.023852008 | M16: =SUMIF($I$5:$I$44,">="&I16)/SUM($I$5:$I$44) -> 0.8163233 | N16: =IF(M16<=0.8,"A",IF(M16<=0.95,"B",IF(M16<=1,"C","C"))) -> B
... A44: P040 | B44: Ceramic Mug Set | C44: Home | D44: Kitchen | E44: 599 | F44: 300 | H44: =SUMIFS('Sales Data'!$M$2:$M$1201,'Sales Data'!$K$2:$K$1201,A44) -> 3 | I44: =SUMIFS('Sales Data'!$P$2:$P$1201,'Sales Data'!$K$2:$K$1201,A44) -> 1707 | J44: =SUMIFS('Sales Data'!$R$2:$R$1201,'Sales Data'!$K$2:$K$1201,A44) -> 807 | K44: =IF(I44=0,0,J44/I44) -> 0.47275923 | L44: =I44/SUM($I$5:$I$44) -> 0.00031455749 | M44: =SUMIF($I$5:$I$44,">="&I44)/SUM($I$5:$I$44) -> 1 | N44: =IF(M44<=0.8,"A",IF(M44<=0.95,"B",IF(M44<=1,"C","C"))) -> C
A46: Note: K = J/I; L = I / total sales; M = share of sales from this product and every product that sold at least as much (ranked cumulative share, ties handled); N: A <= 80%, B <= 95%, C = rest. P031 and P039 had no sales.

Sheet 3 ABC Tasks
A1: 3. Product ABC analysis
A2: Work on the Products sheet, then type your answers in the yellow cells.
A4: No. | B4: Task | C4: Your answer | D4: Done? (Y/N)
A5: 1 | B5: Fill Units Sold, Sales and Profit for all 40 products on the Products sheet. Enter the sum of the Sales (₹) column. | C5: =SUM(Products!$I$5:$I$44) -> 5426671 | D5: Y
A6: 2 | B6: Which product has the highest Sales? Enter the product name. | C6: =INDEX(Products!$B$5:$B$44,MATCH(MAX(Products!$I$5:$I$44),Products!$I$5:$I$44,0)) -> Noise-Cancelling Headphones | D6: Y
A7: 3 | B7: Which product has the highest Profit? Enter the product name. | C7: =INDEX(Products!$B$5:$B$44,MATCH(MAX(Products!$J$5:$J$44),Products!$J$5:$J$44,0)) -> Noise-Cancelling Headphones | D7: Y
A8: 4 | B8: How many products have a negative total Profit? | C8: =COUNTIF(Products!$J$5:$J$44,"<0") -> 1 | D8: Y
A9: 5 | B9: Fill Profit Margin, Sales Share, Cumulative Share and ABC Class (A = cumulative share up to 80%, B = up to 95%, C = the rest). How many products are Class A? | C9: =COUNTIF(Products!$N$5:$N$44,"A") -> 13 | D9: Y
A10: 6 | B10: What share of total Sales do the Class A products make? Enter it as a percentage. | C10: =SUMIF(Products!$N$5:$N$44,"A",Products!$I$5:$I$44)/SUM(Products!$I$5:$I$44) -> 0.7924713 | D10: Y
A11: 7 | B11: How many products sold fewer than 10 units in the year? (dead-stock candidates) | C11: =COUNTIF(Products!$H$5:$H$44,"<10") -> 4 | D11: Y
A12: 8 | B12: Which Category has the highest profit margin? Enter the category name. | C12: =INDEX(Pivots!$A$64:$A$69,MATCH(MAX(Pivots!$E$64:$E$69),Pivots!$E$64:$E$69,0)) -> Beauty | D12: Y
A13: 9 | B13: What is the total Profit (₹) of the Furniture category? | C13: =SUMIFS('Sales Data'!$R$2:$R$1201,'Sales Data'!$I$2:$I$1201,"Furniture") -> 56785 | D13: Y

Sheet Customers
A1: Customers: RFM analysis
A2: Fill down each yellow column from the first row. Use the lookup tables on the right (columns P and Q) with approximate match.
A4: Customer ID | B4: Customer Name | C4: Segment | D4: City | F4: Orders | G4: Last Order Date | H4: Days Since Last Order | I4: Total Sales (₹) | J4: R Score | K4: F Score | L4: M Score | M4: Total Score | N4: RFM Segment | P4: As of date | Q4: 46022 | R4: Fixed so answers do not change (last day of the data)
A5: C001 | B5: Neha Verma | C5: Consumer | D5: Bengaluru | F5: =COUNTIF('Sales Data'!$D$2:$D$1201,A5) -> 4 | G5: =_xlfn.MAXIFS('Sales Data'!$B$2:$B$1201,'Sales Data'!$D$2:$D$1201,A5) -> 45965 | H5: =$Q$4-G5 -> 57 | I5: =SUMIFS('Sales Data'!$P$2:$P$1201,'Sales Data'!$D$2:$D$1201,A5) -> 8654 | J5: =INDEX($Q$7:$Q$9,MATCH(H5,$P$7:$P$9,1)) -> 2 | K5: =INDEX($Q$12:$Q$14,MATCH(F5,$P$12:$P$14,1)) -> 2 | L5: =INDEX($Q$17:$Q$19,MATCH(I5,$P$17:$P$19,1)) -> 1 | M5: =J5+K5+L5 -> 5 | N5: =INDEX($Q$22:$Q$25,MATCH(M5,$P$22:$P$25,1)) -> At Risk
A6: C002 | B6: Ramesh Shah | C6: Consumer | D6: Delhi | F6: =COUNTIF('Sales Data'!$D$2:$D$1201,A6) -> 3 | G6: =_xlfn.MAXIFS('Sales Data'!$B$2:$B$1201,'Sales Data'!$D$2:$D$1201,A6) -> 45882 | H6: =$Q$4-G6 -> 140 | I6: =SUMIFS('Sales Data'!$P$2:$P$1201,'Sales Data'!$D$2:$D$1201,A6) -> 23645 | J6: =INDEX($Q$7:$Q$9,MATCH(H6,$P$7:$P$9,1)) -> 2 | K6: =INDEX($Q$12:$Q$14,MATCH(F6,$P$12:$P$14,1)) -> 2 | L6: =INDEX($Q$17:$Q$19,MATCH(I6,$P$17:$P$19,1)) -> 2 | M6: =J6+K6+L6 -> 6 | N6: =INDEX($Q$22:$Q$25,MATCH(M6,$P$22:$P$25,1)) -> Loyal | P6: Days since last order at least | Q6: R score
A7: C003 | B7: Anjali Kulkarni | C7: Corporate | D7: Kolkata | F7: =COUNTIF('Sales Data'!$D$2:$D$1201,A7) -> 2 | G7: =_xlfn.MAXIFS('Sales Data'!$B$2:$B$1201,'Sales Data'!$D$2:$D$1201,A7) -> 45930 | H7: =$Q$4-G7 -> 92 | I7: =SUMIFS('Sales Data'!$P$2:$P$1201,'Sales Data'!$D$2:$D$1201,A7) -> 1420 | J7: =INDEX($Q$7:$Q$9,MATCH(H7,$P$7:$P$9,1)) -> 2 | K7: =INDEX($Q$12:$Q$14,MATCH(F7,$P$12:$P$14,1)) -> 1 | L7: =INDEX($Q$17:$Q$19,MATCH(I7,$P$17:$P$19,1)) -> 1 | M7: =J7+K7+L7 -> 4 | N7: =INDEX($Q$22:$Q$25,MATCH(M7,$P$22:$P$25,1)) -> At Risk | P7: 0 | Q7: 3
A8: C004 | B8: Manoj Nair | C8: Consumer | D8: Pune | F8: =COUNTIF('Sales Data'!$D$2:$D$1201,A8) -> 7 | G8: =_xlfn.MAXIFS('Sales Data'!$B$2:$B$1201,'Sales Data'!$D$2:$D$1201,A8) -> 46008 | H8: =$Q$4-G8 -> 14 | I8: =SUMIFS('Sales Data'!$P$2:$P$1201,'Sales Data'!$D$2:$D$1201,A8) -> 30772 | J8: =INDEX($Q$7:$Q$9,MATCH(H8,$P$7:$P$9,1)) -> 3 | K8: =INDEX($Q$12:$Q$14,MATCH(F8,$P$12:$P$14,1)) -> 3 | L8: =INDEX($Q$17:$Q$19,MATCH(I8,$P$17:$P$19,1)) -> 2 | M8: =J8+K8+L8 -> 8 | N8: =INDEX($Q$22:$Q$25,MATCH(M8,$P$22:$P$25,1)) -> Champion | P8: 46 | Q8: 2
A9: C005 | B9: Kavya Kulkarni | C9: Consumer | D9: Bengaluru | F9: =COUNTIF('Sales Data'!$D$2:$D$1201,A9) -> 2 | G9: =_xlfn.MAXIFS('Sales Data'!$B$2:$B$1201,'Sales Data'!$D$2:$D$1201,A9) -> 45983 | H9: =$Q$4-G9 -> 39 | I9: =SUMIFS('Sales Data'!$P$2:$P$1201,'Sales Data'!$D$2:$D$1201,A9) -> 4754 | J9: =INDEX($Q$7:$Q$9,MATCH(H9,$P$7:$P$9,1)) -> 3 | K9: =INDEX($Q$12:$Q$14,MATCH(F9,$P$12:$P$14,1)) -> 1 | L9: =INDEX($Q$17:$Q$19,MATCH(I9,$P$17:$P$19,1)) -> 1 | M9: =J9+K9+L9 -> 5 | N9: =INDEX($Q$22:$Q$25,MATCH(M9,$P$22:$P$25,1)) -> At Risk | P9: 151 | Q9: 1
A10: C006 | B10: Kunal Bose | C10: Consumer | D10: Kolkata | F10: =COUNTIF('Sales Data'!$D$2:$D$1201,A10) -> 6 | G10: =_xlfn.MAXIFS('Sales Data'!$B$2:$B$1201,'Sales Data'!$D$2:$D$1201,A10) -> 45999 | H10: =$Q$4-G10 -> 23 | I10: =SUMIFS('Sales Data'!$P$2:$P$1201,'Sales Data'!$D$2:$D$1201,A10) -> 20096 | J10: =INDEX($Q$7:$Q$9,MATCH(H10,$P$7:$P$9,1)) -> 3 | K10: =INDEX($Q$12:$Q$14,MATCH(F10,$P$12:$P$14,1)) -> 2 | L10: =INDEX($Q$17:$Q$19,MATCH(I10,$P$17:$P$19,1)) -> 2 | M10: =J10+K10+L10 -> 7 | N10: =INDEX($Q$22:$Q$25,MATCH(M10,$P$22:$P$25,1)) -> Loyal
A11: C007 | B11: Kavya Patel | C11: Consumer | D11: Pune | F11: =COUNTIF('Sales Data'!$D$2:$D$1201,A11) -> 2 | G11: =_xlfn.MAXIFS('Sales Data'!$B$2:$B$1201,'Sales Data'!$D$2:$D$1201,A11) -> 45866 | H11: =$Q$4-G11 -> 156 | I11: =SUMIFS('Sales Data'!$P$2:$P$1201,'Sales Data'!$D$2:$D$1201,A11) -> 3874 | J11: =INDEX($Q$7:$Q$9,MATCH(H11,$P$7:$P$9,1)) -> 1 | K11: =INDEX($Q$12:$Q$14,MATCH(F11,$P$12:$P$14,1)) -> 1 | L11: =INDEX($Q$17:$Q$19,MATCH(I11,$P$17:$P$19,1)) -> 1 | M11: =J11+K11+L11 -> 3 | N11: =INDEX($Q$22:$Q$25,MATCH(M11,$P$22:$P$25,1)) -> Lost | P11: Orders at least | Q11: F score
A12: C008 | B12: Riya Bose | C12: Home Office | D12: Mumbai | F12: =COUNTIF('Sales Data'!$D$2:$D$1201,A12) -> 7 | G12: =_xlfn.MAXIFS('Sales Data'!$B$2:$B$1201,'Sales Data'!$D$2:$D$1201,A12) -> 45976 | H12: =$Q$4-G12 -> 46 | I12: =SUMIFS('Sales Data'!$P$2:$P$1201,'Sales Data'!$D$2:$D$1201,A12) -> 17849 | J12: =INDEX($Q$7:$Q$9,MATCH(H12,$P$7:$P$9,1)) -> 2 | K12: =INDEX($Q$12:$Q$14,MATCH(F12,$P$12:$P$14,1)) -> 3 | L12: =INDEX($Q$17:$Q$19,MATCH(I12,$P$17:$P$19,1)) -> 2 | M12: =J12+K12+L12 -> 7 | N12: =INDEX($Q$22:$Q$25,MATCH(M12,$P$22:$P$25,1)) -> Loyal | P12: 1 | Q12: 1
A13: C009 | B13: Divya Sharma | C13: Consumer | D13: Chennai | F13: =COUNTIF('Sales Data'!$D$2:$D$1201,A13) -> 4 | G13: =_xlfn.MAXIFS('Sales Data'!$B$2:$B$1201,'Sales Data'!$D$2:$D$1201,A13) -> 45965 | H13: =$Q$4-G13 -> 57 | I13: =SUMIFS('Sales Data'!$P$2:$P$1201,'Sales Data'!$D$2:$D$1201,A13) -> 12094 | J13: =INDEX($Q$7:$Q$9,MATCH(H13,$P$7:$P$9,1)) -> 2 | K13: =INDEX($Q$12:$Q$14,MATCH(F13,$P$12:$P$14,1)) -> 2 | L13: =INDEX($Q$17:$Q$19,MATCH(I13,$P$17:$P$19,1)) -> 2 | M13: =J13+K13+L13 -> 6 | N13: =INDEX($Q$22:$Q$25,MATCH(M13,$P$22:$P$25,1)) -> Loyal | P13: 3 | Q13: 2
A14: C010 | B14: Zoya Das | C14: Home Office | D14: Hyderabad | F14: =COUNTIF('Sales Data'!$D$2:$D$1201,A14) -> 3 | G14: =_xlfn.MAXIFS('Sales Data'!$B$2:$B$1201,'Sales Data'!$D$2:$D$1201,A14) -> 45983 | H14: =$Q$4-G14 -> 39 | I14: =SUMIFS('Sales Data'!$P$2:$P$1201,'Sales Data'!$D$2:$D$1201,A14) -> 15734 | J14: =INDEX($Q$7:$Q$9,MATCH(H14,$P$7:$P$9,1)) -> 3 | K14: =INDEX($Q$12:$Q$14,MATCH(F14,$P$12:$P$14,1)) -> 2 | L14: =INDEX($Q$17:$Q$19,MATCH(I14,$P$17:$P$19,1)) -> 2 | M14: =J14+K14+L14 -> 7 | N14: =INDEX($Q$22:$Q$25,MATCH(M14,$P$22:$P$25,1)) -> Loyal | P14: 7 | Q14: 3
A15: C011 | B15: Isha Shah | C15: Consumer | D15: Pune | F15: =COUNTIF('Sales Data'!$D$2:$D$1201,A15) -> 2 | G15: =_xlfn.MAXIFS('Sales Data'!$B$2:$B$1201,'Sales Data'!$D$2:$D$1201,A15) -> 45953 | H15: =$Q$4-G15 -> 69 | I15: =SUMIFS('Sales Data'!$P$2:$P$1201,'Sales Data'!$D$2:$D$1201,A15) -> 4123 | J15: =INDEX($Q$7:$Q$9,MATCH(H15,$P$7:$P$9,1)) -> 2 | K15: =INDEX($Q$12:$Q$14,MATCH(F15,$P$12:$P$14,1)) -> 1 | L15: =INDEX($Q$17:$Q$19,MATCH(I15,$P$17:$P$19,1)) -> 1 | M15: =J15+K15+L15 -> 4 | N15: =INDEX($Q$22:$Q$25,MATCH(M15,$P$22:$P$25,1)) -> At Risk
A16: C012 | B16: Suresh Desai | C16: Home Office | D16: Bengaluru | F16: =COUNTIF('Sales Data'!$D$2:$D$1201,A16) -> 15 | G16: =_xlfn.MAXIFS('Sales Data'!$B$2:$B$1201,'Sales Data'!$D$2:$D$1201,A16) -> 46012 | H16: =$Q$4-G16 -> 10 | I16: =SUMIFS('Sales Data'!$P$2:$P$1201,'Sales Data'!$D$2:$D$1201,A16) -> 80674 | J16: =INDEX($Q$7:$Q$9,MATCH(H16,$P$7:$P$9,1)) -> 3 | K16: =INDEX($Q$12:$Q$14,MATCH(F16,$P$12:$P$14,1)) -> 3 | L16: =INDEX($Q$17:$Q$19,MATCH(I16,$P$17:$P$19,1)) -> 3 | M16: =J16+K16+L16 -> 9 | N16: =INDEX($Q$22:$Q$25,MATCH(M16,$P$22:$P$25,1)) -> Champion | P16: Total Sales at least (₹) | Q16: M score
A17: C013 | B17: Suresh Malhotra | C17: Consumer | D17: Bengaluru | F17: =COUNTIF('Sales Data'!$D$2:$D$1201,A17) -> 6 | G17: =_xlfn.MAXIFS('Sales Data'!$B$2:$B$1201,'Sales Data'!$D$2:$D$1201,A17) -> 45971 | H17: =$Q$4-G17 -> 51 | I17: =SUMIFS('Sales Data'!$P$2:$P$1201,'Sales Data'!$D$2:$D$1201,A17) -> 28689 | J17: =INDEX($Q$7:$Q$9,MATCH(H17,$P$7:$P$9,1)) -> 2 | K17: =INDEX($Q$12:$Q$14,MATCH(F17,$P$12:$P$14,1)) -> 2 | L17: =INDEX($Q$17:$Q$19,MATCH(I17,$P$17:$P$19,1)) -> 2 | M17: =J17+K17+L17 -> 6 | N17: =INDEX($Q$22:$Q$25,MATCH(M17,$P$22:$P$25,1)) -> Loyal | P17: 0 | Q17: 1
A18: C014 | B18: Rahul Jain | C18: Consumer | D18: Bengaluru | F18: =COUNTIF('Sales Data'!$D$2:$D$1201,A18) -> 10 | G18: =_xlfn.MAXIFS('Sales Data'!$B$2:$B$1201,'Sales Data'!$D$2:$D$1201,A18) -> 46021 | H18: =$Q$4-G18 -> 1 | I18: =SUMIFS('Sales Data'!$P$2:$P$1201,'Sales Data'!$D$2:$D$1201,A18) -> 14043 | J18: =INDEX($Q$7:$Q$9,MATCH(H18,$P$7:$P$9,1)) -> 3 | K18: =INDEX($Q$12:$Q$14,MATCH(F18,$P$12:$P$14,1)) -> 3 | L18: =INDEX($Q$17:$Q$19,MATCH(I18,$P$17:$P$19,1)) -> 2 | M18: =J18+K18+L18 -> 8 | N18: =INDEX($Q$22:$Q$25,MATCH(M18,$P$22:$P$25,1)) -> Champion | P18: 12000 | Q18: 2
A19: C015 | B19: Kavya Gupta | C19: Corporate | D19: Kolkata | F19: =COUNTIF('Sales Data'!$D$2:$D$1201,A19) -> 2 | G19: =_xlfn.MAXIFS('Sales Data'!$B$2:$B$1201,'Sales Data'!$D$2:$D$1201,A19) -> 45879 | H19: =$Q$4-G19 -> 143 | I19: =SUMIFS('Sales Data'!$P$2:$P$1201,'Sales Data'!$D$2:$D$1201,A19) -> 5192 | J19: =INDEX($Q$7:$Q$9,MATCH(H19,$P$7:$P$9,1)) -> 2 | K19: =INDEX($Q$12:$Q$14,MATCH(F19,$P$12:$P$14,1)) -> 1 | L19: =INDEX($Q$17:$Q$19,MATCH(I19,$P$17:$P$19,1)) -> 1 | M19: =J19+K19+L19 -> 4 | N19: =INDEX($Q$22:$Q$25,MATCH(M19,$P$22:$P$25,1)) -> At Risk | P19: 45000 | Q19: 3
A20: C016 | B20: Karan Nair | C20: Corporate | D20: Delhi | F20: =COUNTIF('Sales Data'!$D$2:$D$1201,A20) -> 1 | G20: =_xlfn.MAXIFS('Sales Data'!$B$2:$B$1201,'Sales Data'!$D$2:$D$1201,A20) -> 45811 | H20: =$Q$4-G20 -> 211 | I20: =SUMIFS('Sales Data'!$P$2:$P$1201,'Sales Data'!$D$2:$D$1201,A20) -> 479 | J20: =INDEX($Q$7:$Q$9,MATCH(H20,$P$7:$P$9,1)) -> 1 | K20: =INDEX($Q$12:$Q$14,MATCH(F20,$P$12:$P$14,1)) -> 1 | L20: =INDEX($Q$17:$Q$19,MATCH(I20,$P$17:$P$19,1)) -> 1 | M20: =J20+K20+L20 -> 3 | N20: =INDEX($Q$22:$Q$25,MATCH(M20,$P$22:$P$25,1)) -> Lost
A21: C017 | B21: Manoj Saxena | C21: Home Office | D21: Bengaluru | F21: =COUNTIF('Sales Data'!$D$2:$D$1201,A21) -> 8 | G21: =_xlfn.MAXIFS('Sales Data'!$B$2:$B$1201,'Sales Data'!$D$2:$D$1201,A21) -> 45978 | H21: =$Q$4-G21 -> 44 | I21: =SUMIFS('Sales Data'!$P$2:$P$1201,'Sales Data'!$D$2:$D$1201,A21) -> 44172 | J21: =INDEX($Q$7:$Q$9,MATCH(H21,$P$7:$P$9,1)) -> 3 | K21: =INDEX($Q$12:$Q$14,MATCH(F21,$P$12:$P$14,1)) -> 3 | L21: =INDEX($Q$17:$Q$19,MATCH(I21,$P$17:$P$19,1)) -> 2 | M21: =J21+K21+L21 -> 8 | N21: =INDEX($Q$22:$Q$25,MATCH(M21,$P$22:$P$25,1)) -> Champion | P21: Total score at least | Q21: RFM Segment
A22: C018 | B22: Riya Pillai | C22: Home Office | D22: Mumbai | F22: =COUNTIF('Sales Data'!$D$2:$D$1201,A22) -> 8 | G22: =_xlfn.MAXIFS('Sales Data'!$B$2:$B$1201,'Sales Data'!$D$2:$D$1201,A22) -> 45962 | H22: =$Q$4-G22 -> 60 | I22: =SUMIFS('Sales Data'!$P$2:$P$1201,'Sales Data'!$D$2:$D$1201,A22) -> 61007 | J22: =INDEX($Q$7:$Q$9,MATCH(H22,$P$7:$P$9,1)) -> 2 | K22: =INDEX($Q$12:$Q$14,MATCH(F22,$P$12:$P$14,1)) -> 3 | L22: =INDEX($Q$17:$Q$19,MATCH(I22,$P$17:$P$19,1)) -> 3 | M22: =J22+K22+L22 -> 8 | N22: =INDEX($Q$22:$Q$25,MATCH(M22,$P$22:$P$25,1)) -> Champion | P22: 3 | Q22: Lost
A23: C019 | B23: Mohit Rao | C23: Home Office | D23: Bengaluru | F23: =COUNTIF('Sales Data'!$D$2:$D$1201,A23) -> 10 | G23: =_xlfn.MAXIFS('Sales Data'!$B$2:$B$1201,'Sales Data'!$D$2:$D$1201,A23) -> 46021 | H23: =$Q$4-G23 -> 1 | I23: =SUMIFS('Sales Data'!$P$2:$P$1201,'Sales Data'!$D$2:$D$1201,A23) -> 36413 | J23: =INDEX($Q$7:$Q$9,MATCH(H23,$P$7:$P$9,1)) -> 3 | K23: =INDEX($Q$12:$Q$14,MATCH(F23,$P$12:$P$14,1)) -> 3 | L23: =INDEX($Q$17:$Q$19,MATCH(I23,$P$17:$P$19,1)) -> 2 | M23: =J23+K23+L23 -> 8 | N23: =INDEX($Q$22:$Q$25,MATCH(M23,$P$22:$P$25,1)) -> Champion | P23: 4 | Q23: At Risk
A24: C020 | B24: Rahul Pillai | C24: Corporate | D24: Mumbai | F24: =COUNTIF('Sales Data'!$D$2:$D$1201,A24) -> 4 | G24: =_xlfn.MAXIFS('Sales Data'!$B$2:$B$1201,'Sales Data'!$D$2:$D$1201,A24) -> 45960 | H24: =$Q$4-G24 -> 62 | I24: =SUMIFS('Sales Data'!$P$2:$P$1201,'Sales Data'!$D$2:$D$1201,A24) -> 21612 | J24: =INDEX($Q$7:$Q$9,MATCH(H24,$P$7:$P$9,1)) -> 2 | K24: =INDEX($Q$12:$Q$14,MATCH(F24,$P$12:$P$14,1)) -> 2 | L24: =INDEX($Q$17:$Q$19,MATCH(I24,$P$17:$P$19,1)) -> 2 | M24: =J24+K24+L24 -> 6 | N24: =INDEX($Q$22:$Q$25,MATCH(M24,$P$22:$P$25,1)) -> Loyal | P24: 6 | Q24: Loyal
A25: C021 | B25: Rajat Reddy | C25: Consumer | D25: Mumbai | F25: =COUNTIF('Sales Data'!$D$2:$D$1201,A25) -> 4 | G25: =_xlfn.MAXIFS('Sales Data'!$B$2:$B$1201,'Sales Data'!$D$2:$D$1201,A25) -> 45993 | H25: =$Q$4-G25 -> 29 | I25: =SUMIFS('Sales Data'!$P$2:$P$1201,'Sales Data'!$D$2:$D$1201,A25) -> 11555 | J25: =INDEX($Q$7:$Q$9,MATCH(H25,$P$7:$P$9,1)) -> 3 | K25: =INDEX($Q$12:$Q$14,MATCH(F25,$P$12:$P$14,1)) -> 2 | L25: =INDEX($Q$17:$Q$19,MATCH(I25,$P$17:$P$19,1)) -> 1 | M25: =J25+K25+L25 -> 6 | N25: =INDEX($Q$22:$Q$25,MATCH(M25,$P$22:$P$25,1)) -> Loyal | P25: 8 | Q25: Champion
A26: C022 | B26: Gaurav Saxena | C26: Consumer | D26: Mumbai | F26: =COUNTIF('Sales Data'!$D$2:$D$1201,A26) -> 8 | G26: =_xlfn.MAXIFS('Sales Data'!$B$2:$B$1201,'Sales Data'!$D$2:$D$1201,A26) -> 46016 | H26: =$Q$4-G26 -> 6 | I26: =SUMIFS('Sales Data'!$P$2:$P$1201,'Sales Data'!$D$2:$D$1201,A26) -> 49491 | J26: =INDEX($Q$7:$Q$9,MATCH(H26,$P$7:$P$9,1)) -> 3 | K26: =INDEX($Q$12:$Q$14,MATCH(F26,$P$12:$P$14,1)) -> 3 | L26: =INDEX($Q$17:$Q$19,MATCH(I26,$P$17:$P$19,1)) -> 3 | M26: =J26+K26+L26 -> 9 | N26: =INDEX($Q$22:$Q$25,MATCH(M26,$P$22:$P$25,1)) -> Champion
A27: C023 | B27: Sanjay Saxena | C27: Consumer | D27: Bengaluru | F27: =COUNTIF('Sales Data'!$D$2:$D$1201,A27) -> 1 | G27: =_xlfn.MAXIFS('Sales Data'!$B$2:$B$1201,'Sales Data'!$D$2:$D$1201,A27) -> 45963 | H27: =$Q$4-G27 -> 59 | I27: =SUMIFS('Sales Data'!$P$2:$P$1201,'Sales Data'!$D$2:$D$1201,A27) -> 378 | J27: =INDEX($Q$7:$Q$9,MATCH(H27,$P$7:$P$9,1)) -> 2 | K27: =INDEX($Q$12:$Q$14,MATCH(F27,$P$12:$P$14,1)) -> 1 | L27: =INDEX($Q$17:$Q$19,MATCH(I27,$P$17:$P$19,1)) -> 1 | M27: =J27+K27+L27 -> 4 | N27: =INDEX($Q$22:$Q$25,MATCH(M27,$P$22:$P$25,1)) -> At Risk
A28: C024 | B28: Rajat Bhatt | C28: Consumer | D28: Chennai | F28: =COUNTIF('Sales Data'!$D$2:$D$1201,A28) -> 11 | G28: =_xlfn.MAXIFS('Sales Data'!$B$2:$B$1201,'Sales Data'!$D$2:$D$1201,A28) -> 46015 | H28: =$Q$4-G28 -> 7 | I28: =SUMIFS('Sales Data'!$P$2:$P$1201,'Sales Data'!$D$2:$D$1201,A28) -> 39762 | J28: =INDEX($Q$7:$Q$9,MATCH(H28,$P$7:$P$9,1)) -> 3 | K28: =INDEX($Q$12:$Q$14,MATCH(F28,$P$12:$P$14,1)) -> 3 | L28: =INDEX($Q$17:$Q$19,MATCH(I28,$P$17:$P$19,1)) -> 2 | M28: =J28+K28+L28 -> 8 | N28: =INDEX($Q$22:$Q$25,MATCH(M28,$P$22:$P$25,1)) -> Champion
A29: C025 | B29: Zoya Kulkarni | C29: Corporate | D29: Mumbai | F29: =COUNTIF('Sales Data'!$D$2:$D$1201,A29) -> 11 | G29: =_xlfn.MAXIFS('Sales Data'!$B$2:$B$1201,'Sales Data'!$D$2:$D$1201,A29) -> 45982 | H29: =$Q$4-G29 -> 40 | I29: =SUMIFS('Sales Data'!$P$2:$P$1201,'Sales Data'!$D$2:$D$1201,A29) -> 77585 | J29: =INDEX($Q$7:$Q$9,MATCH(H29,$P$7:$P$9,1)) -> 3 | K29: =INDEX($Q$12:$Q$14,MATCH(F29,$P$12:$P$14,1)) -> 3 | L29: =INDEX($Q$17:$Q$19,MATCH(I29,$P$17:$P$19,1)) -> 3 | M29: =J29+K29+L29 -> 9 | N29: =INDEX($Q$22:$Q$25,MATCH(M29,$P$22:$P$25,1)) -> Champion
A30: C026 | B30: Ramesh Bose | C30: Consumer | D30: Mumbai | F30: =COUNTIF('Sales Data'!$D$2:$D$1201,A30) -> 2 | G30: =_xlfn.MAXIFS('Sales Data'!$B$2:$B$1201,'Sales Data'!$D$2:$D$1201,A30) -> 45980 | H30: =$Q$4-G30 -> 42 | I30: =SUMIFS('Sales Data'!$P$2:$P$1201,'Sales Data'!$D$2:$D$1201,A30) -> 29095 | J30: =INDEX($Q$7:$Q$9,MATCH(H30,$P$7:$P$9,1)) -> 3 | K30: =INDEX($Q$12:$Q$14,MATCH(F30,$P$12:$P$14,1)) -> 1 | L30: =INDEX($Q$17:$Q$19,MATCH(I30,$P$17:$P$19,1)) -> 2 | M30: =J30+K30+L30 -> 6 | N30: =INDEX($Q$22:$Q$25,MATCH(M30,$P$22:$P$25,1)) -> Loyal
A31: C027 | B31: Tanvi Kapoor | C31: Consumer | D31: Mumbai | F31: =COUNTIF('Sales Data'!$D$2:$D$1201,A31) -> 4 | G31: =_xlfn.MAXIFS('Sales Data'!$B$2:$B$1201,'Sales Data'!$D$2:$D$1201,A31) -> 45971 | H31: =$Q$4-G31 -> 51 | I31: =SUMIFS('Sales Data'!$P$2:$P$1201,'Sales Data'!$D$2:$D$1201,A31) -> 16734 | J31: =INDEX($Q$7:$Q$9,MATCH(H31,$P$7:$P$9,1)) -> 2 | K31: =INDEX($Q$12:$Q$14,MATCH(F31,$P$12:$P$14,1)) -> 2 | L31: =INDEX($Q$17:$Q$19,MATCH(I31,$P$17:$P$19,1)) -> 2 | M31: =J31+K31+L31 -> 6 | N31: =INDEX($Q$22:$Q$25,MATCH(M31,$P$22:$P$25,1)) -> Loyal
A32: C028 | B32: Deepak Kulkarni | C32: Consumer | D32: Mumbai | F32: =COUNTIF('Sales Data'!$D$2:$D$1201,A32) -> 3 | G32: =_xlfn.MAXIFS('Sales Data'!$B$2:$B$1201,'Sales Data'!$D$2:$D$1201,A32) -> 45964 | H32: =$Q$4-G32 -> 58 | I32: =SUMIFS('Sales Data'!$P$2:$P$1201,'Sales Data'!$D$2:$D$1201,A32) -> 24946 | J32: =INDEX($Q$7:$Q$9,MATCH(H32,$P$7:$P$9,1)) -> 2 | K32: =INDEX($Q$12:$Q$14,MATCH(F32,$P$12:$P$14,1)) -> 2 | L32: =INDEX($Q$17:$Q$19,MATCH(I32,$P$17:$P$19,1)) -> 2 | M32: =J32+K32+L32 -> 6 | N32: =INDEX($Q$22:$Q$25,MATCH(M32,$P$22:$P$25,1)) -> Loyal
A33: C029 | B33: Rajat Patel | C33: Corporate | D33: Bengaluru | F33: =COUNTIF('Sales Data'!$D$2:$D$1201,A33) -> 3 | G33: =_xlfn.MAXIFS('Sales Data'!$B$2:$B$1201,'Sales Data'!$D$2:$D$1201,A33) -> 45966 | H33: =$Q$4-G33 -> 56 | I33: =SUMIFS('Sales Data'!$P$2:$P$1201,'Sales Data'!$D$2:$D$1201,A33) -> 18195 | J33: =INDEX($Q$7:$Q$9,MATCH(H33,$P$7:$P$9,1)) -> 2 | K33: =INDEX($Q$12:$Q$14,MATCH(F33,$P$12:$P$14,1)) -> 2 | L33: =INDEX($Q$17:$Q$19,MATCH(I33,$P$17:$P$19,1)) -> 2 | M33: =J33+K33+L33 -> 6 | N33: =INDEX($Q$22:$Q$25,MATCH(M33,$P$22:$P$25,1)) -> Loyal
A34: C030 | B34: Anjali Joshi | C34: Corporate | D34: Chennai | F34: =COUNTIF('Sales Data'!$D$2:$D$1201,A34) -> 5 | G34: =_xlfn.MAXIFS('Sales Data'!$B$2:$B$1201,'Sales Data'!$D$2:$D$1201,A34) -> 45957 | H34: =$Q$4-G34 -> 65 | I34: =SUMIFS('Sales Data'!$P$2:$P$1201,'Sales Data'!$D$2:$D$1201,A34) -> 24669 | J34: =INDEX($Q$7:$Q$9,MATCH(H34,$P$7:$P$9,1)) -> 2 | K34: =INDEX($Q$12:$Q$14,MATCH(F34,$P$12:$P$14,1)) -> 2 | L34: =INDEX($Q$17:$Q$19,MATCH(I34,$P$17:$P$19,1)) -> 2 | M34: =J34+K34+L34 -> 6 | N34: =INDEX($Q$22:$Q$25,MATCH(M34,$P$22:$P$25,1)) -> Loyal
A35: C031 | B35: Manoj Bose | C35: Consumer | D35: Ahmedabad | F35: =COUNTIF('Sales Data'!$D$2:$D$1201,A35) -> 6 | G35: =_xlfn.MAXIFS('Sales Data'!$B$2:$B$1201,'Sales Data'!$D$2:$D$1201,A35) -> 45886 | H35: =$Q$4-G35 -> 136 | I35: =SUMIFS('Sales Data'!$P$2:$P$1201,'Sales Data'!$D$2:$D$1201,A35) -> 26370 | J35: =INDEX($Q$7:$Q$9,MATCH(H35,$P$7:$P$9,1)) -> 2 | K35: =INDEX($Q$12:$Q$14,MATCH(F35,$P$12:$P$14,1)) -> 2 | L35: =INDEX($Q$17:$Q$19,MATCH(I35,$P$17:$P$19,1)) -> 2 | M35: =J35+K35+L35 -> 6 | N35: =INDEX($Q$22:$Q$25,MATCH(M35,$P$22:$P$25,1)) -> Loyal
A36: C032 | B36: Tanvi Kumar | C36: Consumer | D36: Bengaluru | F36: =COUNTIF('Sales Data'!$D$2:$D$1201,A36) -> 3 | G36: =_xlfn.MAXIFS('Sales Data'!$B$2:$B$1201,'Sales Data'!$D$2:$D$1201,A36) -> 45983 | H36: =$Q$4-G36 -> 39 | I36: =SUMIFS('Sales Data'!$P$2:$P$1201,'Sales Data'!$D$2:$D$1201,A36) -> 2026 | J36: =INDEX($Q$7:$Q$9,MATCH(H36,$P$7:$P$9,1)) -> 3 | K36: =INDEX($Q$12:$Q$14,MATCH(F36,$P$12:$P$14,1)) -> 2 | L36: =INDEX($Q$17:$Q$19,MATCH(I36,$P$17:$P$19,1)) -> 1 | M36: =J36+K36+L36 -> 6 | N36: =INDEX($Q$22:$Q$25,MATCH(M36,$P$22:$P$25,1)) -> Loyal
A37: C033 | B37: Neha Nair | C37: Consumer | D37: Pune | F37: =COUNTIF('Sales Data'!$D$2:$D$1201,A37) -> 2 | G37: =_xlfn.MAXIFS('Sales Data'!$B$2:$B$1201,'Sales Data'!$D$2:$D$1201,A37) -> 45976 | H37: =$Q$4-G37 -> 46 | I37: =SUMIFS('Sales Data'!$P$2:$P$1201,'Sales Data'!$D$2:$D$1201,A37) -> 11998 | J37: =INDEX($Q$7:$Q$9,MATCH(H37,$P$7:$P$9,1)) -> 2 | K37: =INDEX($Q$12:$Q$14,MATCH(F37,$P$12:$P$14,1)) -> 1 | L37: =INDEX($Q$17:$Q$19,MATCH(I37,$P$17:$P$19,1)) -> 1 | M37: =J37+K37+L37 -> 4 | N37: =INDEX($Q$22:$Q$25,MATCH(M37,$P$22:$P$25,1)) -> At Risk
... A224: C220 | B224: Varun Singh | C224: Corporate | D224: Kolkata | F224: =COUNTIF('Sales Data'!$D$2:$D$1201,A224) -> 2 | G224: =_xlfn.MAXIFS('Sales Data'!$B$2:$B$1201,'Sales Data'!$D$2:$D$1201,A224) -> 45891 | H224: =$Q$4-G224 -> 131 | I224: =SUMIFS('Sales Data'!$P$2:$P$1201,'Sales Data'!$D$2:$D$1201,A224) -> 2846 | J224: =INDEX($Q$7:$Q$9,MATCH(H224,$P$7:$P$9,1)) -> 2 | K224: =INDEX($Q$12:$Q$14,MATCH(F224,$P$12:$P$14,1)) -> 1 | L224: =INDEX($Q$17:$Q$19,MATCH(I224,$P$17:$P$19,1)) -> 1 | M224: =J224+K224+L224 -> 4 | N224: =INDEX($Q$22:$Q$25,MATCH(M224,$P$22:$P$25,1)) -> At Risk

Sheet 4 RFM Tasks
A1: 4. Customer RFM analysis
A2: Work on the Customers sheet, then type your answers in the yellow cells.
A4: No. | B4: Task | C4: Your answer | D4: Done? (Y/N)
A5: 1 | B5: Fill Orders, Last Order Date, Days Since Last Order and Total Sales on the Customers sheet. How many customers ordered only once? | C5: =COUNTIF(Customers!$F$5:$F$224,1) -> 29 | D5: Y
A6: 2 | B6: Which customer has the highest Total Sales? Enter the Customer ID. | C6: =INDEX(Customers!$A$5:$A$224,MATCH(MAX(Customers!$I$5:$I$224),Customers!$I$5:$I$224,0)) -> C166 | D6: Y
A7: 3 | B7: What is the highest number of orders placed by one customer? | C7: =MAX(Customers!$F$5:$F$224) -> 20 | D7: Y
A8: 4 | B8: Fill the R, F and M scores, Total Score and RFM Segment using the lookup tables. How many customers are Champions? | C8: =COUNTIF(Customers!$N$5:$N$224,"Champion") -> 67 | D8: Y
A9: 5 | B9: How many customers are Loyal? | C9: =COUNTIF(Customers!$N$5:$N$224,"Loyal") -> 76 | D9: Y
A10: 6 | B10: How many customers are At Risk? | C10: =COUNTIF(Customers!$N$5:$N$224,"At Risk") -> 56 | D10: Y
A11: 7 | B11: How many customers are Lost? | C11: =COUNTIF(Customers!$N$5:$N$224,"Lost") -> 21 | D11: Y
A12: 8 | B12: What are the total Sales (₹) from Champion customers? | C12: =SUMIF(Customers!$N$5:$N$224,"Champion",Customers!$I$5:$I$224) -> 3394545 | D12: Y
A13: 9 | B13: What percentage of all Sales comes from Champion customers? | C13: =C12/SUM(Customers!$I$5:$I$224) -> 0.62552991 | D13: Y

Sheet 5 Dashboard Tasks
A1: 5. Pivot tables, charts and dashboard
A2: Use the Sales Data sheet (or your Sales_Clean query table). Type your answers in the yellow cells.
A4: No. | B4: Task | C4: Your answer | D4: Done? (Y/N)
A5: 1 | B5: Build a PivotTable from Sales Data (put each pivot on its own sheet). Rows = Region, Values = Sum of Sales (₹). Enter the Sales for West. | C5: =Pivots!$B$9 -> 2190302 | D5: Y
A6: 2 | B6: Rows = Category, Columns = Region, Values = Sum of Sales (₹). Enter the value for Electronics in the South column. | C6: =Pivots!$D$16 -> 590693 | D6: Y
A7: 3 | B7: Put Order Date in Rows and group by Months and Quarters. Enter the total Sales (₹) for Quarter 4. | C7: =Pivots!$I$27 -> 1978359 | D7: Y
A8: 4 | B8: Rows = Sub-Category, Values = Sum of Profit (₹), sorted from largest to smallest. Enter the name of the top Sub-Category. | C8: =Pivots!$A$40 -> Audio | D8: Y
A9: 5 | B9: Show Values As > % of Grand Total for Profit by Category. Enter the % for Electronics. | C9: =Pivots!$D$66 -> 0.36928395 | D9: Y
A10: 6 | B10: Add a calculated field Profit Margin = Profit / Sales. Enter the margin for Furniture as a percentage. | C10: =Pivots!$E$67 -> 0.033960594 | D10: Y
A11: 7 | B11: Add a helper column Discount Band on Sales Data (No discount, Up to 20%, Above 20%) and pivot Profit by band. Enter the Profit (₹) for Above 20%. | C11: =SUMIFS('Sales Data'!$R$2:$R$1201,'Sales Data'!$T$2:$T$1201,"Above 20%") -> -47109 | D11: Y
A12: 8 | B12: Insert a pivot chart (clustered column) of Sales by Region and give it a clear title. Mark Y when done. | C12: Y: column chart on the Pivots sheet (regular chart; convert to a PivotChart in Excel) | D12: Y
A13: 9 | B13: Insert slicers for Category and Region and connect them to two pivot tables. Check that both change together. Mark Y when done. | C13: Do in Excel: Insert > Slicer (see README step 5) | D13: N
A14: 10 | B14: Insert a timeline slicer on Order Date and connect it to the same pivot tables. Mark Y when done. | C14: Do in Excel: Insert > Timeline (see README step 5) | D14: N
A15: 11 | B15: Build a one-page dashboard: four KPI cards (Sales, Profit, Margin, Orders), three charts, the slicers and the timeline. Set it to print on one page. Mark Y when done. | C15: Y: Dashboard sheet (4 KPI cards, 3 charts, Region/Category dropdowns, date range, prints on 1 page) | D15: Y
A16: 12 | B16: Click Data > Refresh All and confirm every pivot, chart and KPI card updates. Mark Y when done. | C16: Do in Excel after loading the Power Query | D16: N

Sheet Dashboard
B2: Retail Sales & Profit Dashboard | FY 2025 (₹)
B3: 1,200 cleaned orders, Jan to Dec 2025. Change the yellow cells below and every card and chart updates.
B5: Region | C5: All | D5: Category | E5: All | F5: From | G5: 45658 | H5: To | I5: 46022 | J5: Dropdowns: pick a Region or Category (or All). Type a From / To date.
B7: TOTAL SALES | E7: TOTAL PROFIT | H7: PROFIT MARGIN | K7: ORDERS
B8: =Dash_Calc!B47 -> 5426671 | E8: =Dash_Calc!B48 -> 1212441 | H8: =Dash_Calc!B49 -> 0.22342261 | K8: =Dash_Calc!B50 -> 1200
B10: ="Share of full year: "&TEXT(Dash_Calc!B52,"0.0%") -> Share of full year: 100.0% | E10: ="Share of full year: "&TEXT(Dash_Calc!B53,"0.0%") -> Share of full year: 100.0% | H10: ="Full-year margin: "&TEXT(Dash_Calc!B54,"0.0%") -> Full-year margin: 22.3% | K10: ="Avg order value: ₹"&TEXT(Dash_Calc!B51,"#,##0") -> Avg order value: ₹4,522
H29: Profit by Discount Band (follows the filters)
H30: Band | J30: Orders | K30: Sales (₹) | L30: Profit (₹) | M30: Margin
H31: =Dash_Calc!A41 -> No discount | J31: =Dash_Calc!B41 -> 367 | K31: =Dash_Calc!C41 -> 1494101 | L31: =Dash_Calc!D41 -> 541151 | M31: =Dash_Calc!E41 -> 0.36219171
H32: =Dash_Calc!A42 -> Up to 20% | J32: =Dash_Calc!B42 -> 643 | K32: =Dash_Calc!C42 -> 3062479 | L32: =Dash_Calc!D42 -> 718399 | M32: =Dash_Calc!E42 -> 0.23458087
H33: =Dash_Calc!A43 -> Above 20% | J33: =Dash_Calc!B43 -> 190 | K33: =Dash_Calc!C43 -> 870091 | L33: =Dash_Calc!D43 -> -47109 | M33: =Dash_Calc!E43 -> -0.054142613
H35: Reading it: orders discounted above 20% earn a negative margin, while orders with no discount earn the highest margin. Pick a Category to see if the pattern holds there.
B46: Source: Sales Data sheet (Sales_Clean). Profit = Sales - Cost. All amounts in Indian rupees (₹).

Sheet Pivots
A1: Pivot-style summary tables
A2: Every table is a live SUMIFS/COUNTIFS formula on the Sales Data sheet, so it recalculates when the data changes. Equivalent PivotTables can be inserted in Excel (steps in the repo README).
A4: Pivot 1: Sales (₹) by Region
A5: Region | B5: Sales (₹)
A6: East | B6: =SUMIFS('Sales Data'!$P$2:$P$1201,'Sales Data'!$G$2:$G$1201,A6) -> 333766
A7: North | B7: =SUMIFS('Sales Data'!$P$2:$P$1201,'Sales Data'!$G$2:$G$1201,A7) -> 1155087
A8: South | B8: =SUMIFS('Sales Data'!$P$2:$P$1201,'Sales Data'!$G$2:$G$1201,A8) -> 1747516
A9: West | B9: =SUMIFS('Sales Data'!$P$2:$P$1201,'Sales Data'!$G$2:$G$1201,A9) -> 2190302
A10: Grand Total | B10: =SUM(B6:B9) -> 5426671
A12: Pivot 2: Sales (₹) by Category and Region
A13: Category | B13: East | C13: North | D13: South | E13: West | F13: Grand Total
A14: Apparel | B14: =SUMIFS('Sales Data'!$P$2:$P$1201,'Sales Data'!$I$2:$I$1201,$A14,'Sales Data'!$G$2:$G$1201,B$13) -> 65872 | C14: =SUMIFS('Sales Data'!$P$2:$P$1201,'Sales Data'!$I$2:$I$1201,$A14,'Sales Data'!$G$2:$G$1201,C$13) -> 170807 | D14: =SUMIFS('Sales Data'!$P$2:$P$1201,'Sales Data'!$I$2:$I$1201,$A14,'Sales Data'!$G$2:$G$1201,D$13) -> 223042 | E14: =SUMIFS('Sales Data'!$P$2:$P$1201,'Sales Data'!$I$2:$I$1201,$A14,'Sales Data'!$G$2:$G$1201,E$13) -> 266310 | F14: =SUM(B14:E14) -> 726031
A15: Beauty | B15: =SUMIFS('Sales Data'!$P$2:$P$1201,'Sales Data'!$I$2:$I$1201,$A15,'Sales Data'!$G$2:$G$1201,B$13) -> 20232 | C15: =SUMIFS('Sales Data'!$P$2:$P$1201,'Sales Data'!$I$2:$I$1201,$A15,'Sales Data'!$G$2:$G$1201,C$13) -> 58381 | D15: =SUMIFS('Sales Data'!$P$2:$P$1201,'Sales Data'!$I$2:$I$1201,$A15,'Sales Data'!$G$2:$G$1201,D$13) -> 101907 | E15: =SUMIFS('Sales Data'!$P$2:$P$1201,'Sales Data'!$I$2:$I$1201,$A15,'Sales Data'!$G$2:$G$1201,E$13) -> 133384 | F15: =SUM(B15:E15) -> 313904
A16: Electronics | B16: =SUMIFS('Sales Data'!$P$2:$P$1201,'Sales Data'!$I$2:$I$1201,$A16,'Sales Data'!$G$2:$G$1201,B$13) -> 55821 | C16: =SUMIFS('Sales Data'!$P$2:$P$1201,'Sales Data'!$I$2:$I$1201,$A16,'Sales Data'!$G$2:$G$1201,C$13) -> 255561 | D16: =SUMIFS('Sales Data'!$P$2:$P$1201,'Sales Data'!$I$2:$I$1201,$A16,'Sales Data'!$G$2:$G$1201,D$13) -> 590693 | E16: =SUMIFS('Sales Data'!$P$2:$P$1201,'Sales Data'!$I$2:$I$1201,$A16,'Sales Data'!$G$2:$G$1201,E$13) -> 766140 | F16: =SUM(B16:E16) -> 1668215
A17: Furniture | B17: =SUMIFS('Sales Data'!$P$2:$P$1201,'Sales Data'!$I$2:$I$1201,$A17,'Sales Data'!$G$2:$G$1201,B$13) -> 109431 | C17: =SUMIFS('Sales Data'!$P$2:$P$1201,'Sales Data'!$I$2:$I$1201,$A17,'Sales Data'!$G$2:$G$1201,C$13) -> 489365 | D17: =SUMIFS('Sales Data'!$P$2:$P$1201,'Sales Data'!$I$2:$I$1201,$A17,'Sales Data'!$G$2:$G$1201,D$13) -> 516346 | E17: =SUMIFS('Sales Data'!$P$2:$P$1201,'Sales Data'!$I$2:$I$1201,$A17,'Sales Data'!$G$2:$G$1201,E$13) -> 556943 | F17: =SUM(B17:E17) -> 1672085
A18: Home | B18: =SUMIFS('Sales Data'!$P$2:$P$1201,'Sales Data'!$I$2:$I$1201,$A18,'Sales Data'!$G$2:$G$1201,B$13) -> 63623 | C18: =SUMIFS('Sales Data'!$P$2:$P$1201,'Sales Data'!$I$2:$I$1201,$A18,'Sales Data'!$G$2:$G$1201,C$13) -> 147972 | D18: =SUMIFS('Sales Data'!$P$2:$P$1201,'Sales Data'!$I$2:$I$1201,$A18,'Sales Data'!$G$2:$G$1201,D$13) -> 239056 | E18: =SUMIFS('Sales Data'!$P$2:$P$1201,'Sales Data'!$I$2:$I$1201,$A18,'Sales Data'!$G$2:$G$1201,E$13) -> 369199 | F18: =SUM(B18:E18) -> 819850
A19: Stationery | B19: =SUMIFS('Sales Data'!$P$2:$P$1201,'Sales Data'!$I$2:$I$1201,$A19,'Sales Data'!$G$2:$G$1201,B$13) -> 18787 | C19: =SUMIFS('Sales Data'!$P$2:$P$1201,'Sales Data'!$I$2:$I$1201,$A19,'Sales Data'!$G$2:$G$1201,C$13) -> 33001 | D19: =SUMIFS('Sales Data'!$P$2:$P$1201,'Sales Data'!$I$2:$I$1201,$A19,'Sales Data'!$G$2:$G$1201,D$13) -> 76472 | E19: =SUMIFS('Sales Data'!$P$2:$P$1201,'Sales Data'!$I$2:$I$1201,$A19,'Sales Data'!$G$2:$G$1201,E$13) -> 98326 | F19: =SUM(B19:E19) -> 226586
A20: Grand Total | B20: =SUM(B14:B19) -> 333766 | C20: =SUM(C14:C19) -> 1155087 | D20: =SUM(D14:D19) -> 1747516 | E20: =SUM(E14:E19) -> 2190302 | F20: =SUM(F14:F19) -> 5426671
A22: Pivot 3: Sales, Profit and Orders by Month and Quarter
A23: Month no. | B23: Month | C23: Quarter | D23: Sales (₹) | E23: Profit (₹) | F23: Orders | H23: Quarter | I23: Sales (₹) | J23: Profit (₹) | K23: Share of Sales
A24: 1 | B24: =TEXT(DATE(2025,A24,1),"mmmm") -> January | C24: ="Qtr"&ROUNDUP(A24/3,0) -> Qtr1 | D24: =SUMPRODUCT((MONTH('Sales Data'!$B$2:$B$1201)=A24)*'Sales Data'!$P$2:$P$1201) -> 305327 | E24: =SUMPRODUCT((MONTH('Sales Data'!$B$2:$B$1201)=A24)*'Sales Data'!$R$2:$R$1201) -> 78507 | F24: =SUMPRODUCT(--(MONTH('Sales Data'!$B$2:$B$1201)=A24)) -> 85 | H24: Qtr1 | I24: =SUMIFS($D$24:$D$35,$C$24:$C$35,H24) -> 915428 | J24: =SUMIFS($E$24:$E$35,$C$24:$C$35,H24) -> 180408 | K24: =I24/$I$28 -> 0.16869053
A25: 2 | B25: =TEXT(DATE(2025,A25,1),"mmmm") -> February | C25: ="Qtr"&ROUNDUP(A25/3,0) -> Qtr1 | D25: =SUMPRODUCT((MONTH('Sales Data'!$B$2:$B$1201)=A25)*'Sales Data'!$P$2:$P$1201) -> 310888 | E25: =SUMPRODUCT((MONTH('Sales Data'!$B$2:$B$1201)=A25)*'Sales Data'!$R$2:$R$1201) -> 47508 | F25: =SUMPRODUCT(--(MONTH('Sales Data'!$B$2:$B$1201)=A25)) -> 64 | H25: Qtr2 | I25: =SUMIFS($D$24:$D$35,$C$24:$C$35,H25) -> 1367989 | J25: =SUMIFS($E$24:$E$35,$C$24:$C$35,H25) -> 295359 | K25: =I25/$I$28 -> 0.25208622
A26: 3 | B26: =TEXT(DATE(2025,A26,1),"mmmm") -> March | C26: ="Qtr"&ROUNDUP(A26/3,0) -> Qtr1 | D26: =SUMPRODUCT((MONTH('Sales Data'!$B$2:$B$1201)=A26)*'Sales Data'!$P$2:$P$1201) -> 299213 | E26: =SUMPRODUCT((MONTH('Sales Data'!$B$2:$B$1201)=A26)*'Sales Data'!$R$2:$R$1201) -> 54393 | F26: =SUMPRODUCT(--(MONTH('Sales Data'!$B$2:$B$1201)=A26)) -> 77 | H26: Qtr3 | I26: =SUMIFS($D$24:$D$35,$C$24:$C$35,H26) -> 1164895 | J26: =SUMIFS($E$24:$E$35,$C$24:$C$35,H26) -> 276095 | K26: =I26/$I$28 -> 0.21466107
A27: 4 | B27: =TEXT(DATE(2025,A27,1),"mmmm") -> April | C27: ="Qtr"&ROUNDUP(A27/3,0) -> Qtr2 | D27: =SUMPRODUCT((MONTH('Sales Data'!$B$2:$B$1201)=A27)*'Sales Data'!$P$2:$P$1201) -> 424765 | E27: =SUMPRODUCT((MONTH('Sales Data'!$B$2:$B$1201)=A27)*'Sales Data'!$R$2:$R$1201) -> 90505 | F27: =SUMPRODUCT(--(MONTH('Sales Data'!$B$2:$B$1201)=A27)) -> 79 | H27: Qtr4 | I27: =SUMIFS($D$24:$D$35,$C$24:$C$35,H27) -> 1978359 | J27: =SUMIFS($E$24:$E$35,$C$24:$C$35,H27) -> 460579 | K27: =I27/$I$28 -> 0.36456218
A28: 5 | B28: =TEXT(DATE(2025,A28,1),"mmmm") -> May | C28: ="Qtr"&ROUNDUP(A28/3,0) -> Qtr2 | D28: =SUMPRODUCT((MONTH('Sales Data'!$B$2:$B$1201)=A28)*'Sales Data'!$P$2:$P$1201) -> 444324 | E28: =SUMPRODUCT((MONTH('Sales Data'!$B$2:$B$1201)=A28)*'Sales Data'!$R$2:$R$1201) -> 89104 | F28: =SUMPRODUCT(--(MONTH('Sales Data'!$B$2:$B$1201)=A28)) -> 94 | H28: Grand Total | I28: =SUM(I24:I27) -> 5426671 | J28: =SUM(J24:J27) -> 1212441 | K28: =SUM(K24:K27) -> 1
A29: 6 | B29: =TEXT(DATE(2025,A29,1),"mmmm") -> June | C29: ="Qtr"&ROUNDUP(A29/3,0) -> Qtr2 | D29: =SUMPRODUCT((MONTH('Sales Data'!$B$2:$B$1201)=A29)*'Sales Data'!$P$2:$P$1201) -> 498900 | E29: =SUMPRODUCT((MONTH('Sales Data'!$B$2:$B$1201)=A29)*'Sales Data'!$R$2:$R$1201) -> 115750 | F29: =SUMPRODUCT(--(MONTH('Sales Data'!$B$2:$B$1201)=A29)) -> 83
A30: 7 | B30: =TEXT(DATE(2025,A30,1),"mmmm") -> July | C30: ="Qtr"&ROUNDUP(A30/3,0) -> Qtr3 | D30: =SUMPRODUCT((MONTH('Sales Data'!$B$2:$B$1201)=A30)*'Sales Data'!$P$2:$P$1201) -> 418685 | E30: =SUMPRODUCT((MONTH('Sales Data'!$B$2:$B$1201)=A30)*'Sales Data'!$R$2:$R$1201) -> 92285 | F30: =SUMPRODUCT(--(MONTH('Sales Data'!$B$2:$B$1201)=A30)) -> 94
A31: 8 | B31: =TEXT(DATE(2025,A31,1),"mmmm") -> August | C31: ="Qtr"&ROUNDUP(A31/3,0) -> Qtr3 | D31: =SUMPRODUCT((MONTH('Sales Data'!$B$2:$B$1201)=A31)*'Sales Data'!$P$2:$P$1201) -> 379426 | E31: =SUMPRODUCT((MONTH('Sales Data'!$B$2:$B$1201)=A31)*'Sales Data'!$R$2:$R$1201) -> 90066 | F31: =SUMPRODUCT(--(MONTH('Sales Data'!$B$2:$B$1201)=A31)) -> 98
A32: 9 | B32: =TEXT(DATE(2025,A32,1),"mmmm") -> September | C32: ="Qtr"&ROUNDUP(A32/3,0) -> Qtr3 | D32: =SUMPRODUCT((MONTH('Sales Data'!$B$2:$B$1201)=A32)*'Sales Data'!$P$2:$P$1201) -> 366784 | E32: =SUMPRODUCT((MONTH('Sales Data'!$B$2:$B$1201)=A32)*'Sales Data'!$R$2:$R$1201) -> 93744 | F32: =SUMPRODUCT(--(MONTH('Sales Data'!$B$2:$B$1201)=A32)) -> 97
A33: 10 | B33: =TEXT(DATE(2025,A33,1),"mmmm") -> October | C33: ="Qtr"&ROUNDUP(A33/3,0) -> Qtr4 | D33: =SUMPRODUCT((MONTH('Sales Data'!$B$2:$B$1201)=A33)*'Sales Data'!$P$2:$P$1201) -> 668213 | E33: =SUMPRODUCT((MONTH('Sales Data'!$B$2:$B$1201)=A33)*'Sales Data'!$R$2:$R$1201) -> 169513 | F33: =SUMPRODUCT(--(MONTH('Sales Data'!$B$2:$B$1201)=A33)) -> 149
A34: 11 | B34: =TEXT(DATE(2025,A34,1),"mmmm") -> November | C34: ="Qtr"&ROUNDUP(A34/3,0) -> Qtr4 | D34: =SUMPRODUCT((MONTH('Sales Data'!$B$2:$B$1201)=A34)*'Sales Data'!$P$2:$P$1201) -> 776952 | E34: =SUMPRODUCT((MONTH('Sales Data'!$B$2:$B$1201)=A34)*'Sales Data'!$R$2:$R$1201) -> 176062 | F34: =SUMPRODUCT(--(MONTH('Sales Data'!$B$2:$B$1201)=A34)) -> 168
A35: 12 | B35: =TEXT(DATE(2025,A35,1),"mmmm") -> December | C35: ="Qtr"&ROUNDUP(A35/3,0) -> Qtr4 | D35: =SUMPRODUCT((MONTH('Sales Data'!$B$2:$B$1201)=A35)*'Sales Data'!$P$2:$P$1201) -> 533194 | E35: =SUMPRODUCT((MONTH('Sales Data'!$B$2:$B$1201)=A35)*'Sales Data'!$R$2:$R$1201) -> 115004 | F35: =SUMPRODUCT(--(MONTH('Sales Data'!$B$2:$B$1201)=A35)) -> 112
A36: Grand Total | D36: =SUM(D24:D35) -> 5426671 | E36: =SUM(E24:E35) -> 1212441 | F36: =SUM(F24:F35) -> 1200
A38: Pivot 4: Profit (₹) by Sub-Category, largest to smallest
A39: Sub-Category | B39: Profit (₹)
A40: Audio | B40: =SUMIFS('Sales Data'!$R$2:$R$1201,'Sales Data'!$J$2:$J$1201,A40) -> 305967
A41: Kitchen | B41: =SUMIFS('Sales Data'!$R$2:$R$1201,'Sales Data'!$J$2:$J$1201,A41) -> 142631
A42: Accessories | B42: =SUMIFS('Sales Data'!$R$2:$R$1201,'Sales Data'!$J$2:$J$1201,A42) -> 92704
A43: Footwear | B43: =SUMIFS('Sales Data'!$R$2:$R$1201,'Sales Data'!$J$2:$J$1201,A43) -> 92095
A44: Decor | B44: =SUMIFS('Sales Data'!$R$2:$R$1201,'Sales Data'!$J$2:$J$1201,A44) -> 82731
A45: Desk | B45: =SUMIFS('Sales Data'!$R$2:$R$1201,'Sales Data'!$J$2:$J$1201,A45) -> 72277
A46: Fragrance | B46: =SUMIFS('Sales Data'!$R$2:$R$1201,'Sales Data'!$J$2:$J$1201,A46) -> 60437
A47: Bottomwear | B47: =SUMIFS('Sales Data'!$R$2:$R$1201,'Sales Data'!$J$2:$J$1201,A47) -> 50622
A48: Wearables | B48: =SUMIFS('Sales Data'!$R$2:$R$1201,'Sales Data'!$J$2:$J$1201,A48) -> 49064
A49: Skincare | B49: =SUMIFS('Sales Data'!$R$2:$R$1201,'Sales Data'!$J$2:$J$1201,A49) -> 42913
A50: Seating | B50: =SUMIFS('Sales Data'!$R$2:$R$1201,'Sales Data'!$J$2:$J$1201,A50) -> 42030
A51: Outerwear | B51: =SUMIFS('Sales Data'!$R$2:$R$1201,'Sales Data'!$J$2:$J$1201,A51) -> 31164
... A59: Storage | B59: =SUMIFS('Sales Data'!$R$2:$R$1201,'Sales Data'!$J$2:$J$1201,A59) -> -9935
A60: Grand Total | B60: =SUM(B40:B59) -> 1212441
A62: Pivot 5 and 6: Category profit, % of grand total profit, and Profit Margin (calculated field = Profit / Sales)
A63: Category | B63: Sales (₹) | C63: Profit (₹) | D63: % of Grand Total Profit | E63: Profit Margin
A64: Apparel | B64: =SUMIFS('Sales Data'!$P$2:$P$1201,'Sales Data'!$I$2:$I$1201,A64) -> 726031 | C64: =SUMIFS('Sales Data'!$R$2:$R$1201,'Sales Data'!$I$2:$I$1201,A64) -> 200041 | D64: =C64/$C$70 -> 0.1649903 | E64: =IF(B64=0,0,C64/B64) -> 0.2755268
A65: Beauty | B65: =SUMIFS('Sales Data'!$P$2:$P$1201,'Sales Data'!$I$2:$I$1201,A65) -> 313904 | C65: =SUMIFS('Sales Data'!$R$2:$R$1201,'Sales Data'!$I$2:$I$1201,A65) -> 154704 | D65: =C65/$C$70 -> 0.12759714 | E65: =IF(B65=0,0,C65/B65) -> 0.49283857
A66: Electronics | B66: =SUMIFS('Sales Data'!$P$2:$P$1201,'Sales Data'!$I$2:$I$1201,A66) -> 1668215 | C66: =SUMIFS('Sales Data'!$R$2:$R$1201,'Sales Data'!$I$2:$I$1201,A66) -> 447735 | D66: =C66/$C$70 -> 0.36928395 | E66: =IF(B66=0,0,C66/B66) -> 0.26839166
A67: Furniture | B67: =SUMIFS('Sales Data'!$P$2:$P$1201,'Sales Data'!$I$2:$I$1201,A67) -> 1672085 | C67: =SUMIFS('Sales Data'!$R$2:$R$1201,'Sales Data'!$I$2:$I$1201,A67) -> 56785 | D67: =C67/$C$70 -> 0.046835269 | E67: =IF(B67=0,0,C67/B67) -> 0.033960594
A68: Home | B68: =SUMIFS('Sales Data'!$P$2:$P$1201,'Sales Data'!$I$2:$I$1201,A68) -> 819850 | C68: =SUMIFS('Sales Data'!$R$2:$R$1201,'Sales Data'!$I$2:$I$1201,A68) -> 256160 | D68: =C68/$C$70 -> 0.21127626 | E68: =IF(B68=0,0,C68/B68) -> 0.3124474
A69: Stationery | B69: =SUMIFS('Sales Data'!$P$2:$P$1201,'Sales Data'!$I$2:$I$1201,A69) -> 226586 | C69: =SUMIFS('Sales Data'!$R$2:$R$1201,'Sales Data'!$I$2:$I$1201,A69) -> 97016 | D69: =C69/$C$70 -> 0.080017089 | E69: =IF(B69=0,0,C69/B69) -> 0.42816414
A70: Grand Total | B70: =SUM(B64:B69) -> 5426671 | C70: =SUM(C64:C69) -> 1212441 | D70: =SUM(D64:D69) -> 1 | E70: =C70/B70 -> 0.22342261
A72: Pivot 7: Orders, Sales and Profit by Discount Band (helper column T on Sales Data)
A73: Discount Band | B73: Orders | C73: Sales (₹) | D73: Profit (₹) | E73: Profit Margin
A74: No discount | B74: =COUNTIF('Sales Data'!$T$2:$T$1201,A74) -> 367 | C74: =SUMIFS('Sales Data'!$P$2:$P$1201,'Sales Data'!$T$2:$T$1201,A74) -> 1494101 | D74: =SUMIFS('Sales Data'!$R$2:$R$1201,'Sales Data'!$T$2:$T$1201,A74) -> 541151 | E74: =IF(C74=0,0,D74/C74) -> 0.36219171
A75: Up to 20% | B75: =COUNTIF('Sales Data'!$T$2:$T$1201,A75) -> 643 | C75: =SUMIFS('Sales Data'!$P$2:$P$1201,'Sales Data'!$T$2:$T$1201,A75) -> 3062479 | D75: =SUMIFS('Sales Data'!$R$2:$R$1201,'Sales Data'!$T$2:$T$1201,A75) -> 718399 | E75: =IF(C75=0,0,D75/C75) -> 0.23458087
A76: Above 20% | B76: =COUNTIF('Sales Data'!$T$2:$T$1201,A76) -> 190 | C76: =SUMIFS('Sales Data'!$P$2:$P$1201,'Sales Data'!$T$2:$T$1201,A76) -> 870091 | D76: =SUMIFS('Sales Data'!$R$2:$R$1201,'Sales Data'!$T$2:$T$1201,A76) -> -47109 | E76: =IF(C76=0,0,D76/C76) -> -0.054142613
A77: Grand Total | B77: =SUM(B74:B76) -> 1200 | C77: =SUM(C74:C76) -> 5426671 | D77: =SUM(D74:D76) -> 1212441 | E77: =D77/C77 -> 0.22342261

Sheet 6 Insights
A1: 6. Insights and recommendations
A2: Write five findings, each with a number from your analysis and an action a shop owner can take. The grey row shows the format.
A4: No. | B4: Finding (plain language) | C4: Evidence (a number from your work) | D4: Recommendation | E4: Estimated impact (₹)
A5: Ex. | B5: Deep discounts turn orders into losses. | C5: ="Orders with a discount above 20% lost ₹"&TEXT(-SUMIFS('Sales Data'!$R$2:$R$1201,'Sales Data'!$O$2:$O$1201,">0.2"),"#,##0")&" in total." -> Orders with a discount above 20% lost ₹47,109 in total. | D5: Cap discounts at 20% for low-margin categories and review prices of the loss-making products. | E5: =-SUMIFS('Sales Data'!$R$2:$R$1201,'Sales Data'!$O$2:$O$1201,">0.2") -> 47109
A6: 1 | B6: Discounts above 20% destroy profit: this band loses money while undiscounted orders earn the best margin. | C6: ="Orders above 20% discount: "&Pivots!$B$76&" ("&TEXT(Pivots!$B$76/Pivots!$B$77,"0%")&" of all orders) with a profit of -₹"&TEXT(-Pivots!$D$76,"#,##0")&" (margin "&TEXT(Pivots!$E$76,"0.0%")&"). No-discount orders earned "&TEXT(Pivots!$E$74,"0.0%")&"." -> Orders above 20% discount: 190 (16% of all orders) with a profit of -₹47,109 (margin -5.4%). No-discount orders earned 36.2%. | D6: Cap discounts at 20% and require manager approval above that. Review the 30 to 50% discounts on Furniture first. | E6: =-SUMIFS('Sales Data'!$R$2:$R$1201,'Sales Data'!$O$2:$O$1201,">0.2") -> 47109
A7: 2 | B7: Furniture brings a third of the sales but almost no profit; Bookshelf is a top seller that loses money. | C7: ="Furniture is "&TEXT(Pivots!$B$67/Pivots!$B$70,"0%")&" of sales but only "&TEXT(Pivots!$E$67,"0.0%")&" margin (₹"&TEXT(Pivots!$C$67,"#,##0")&"). Bookshelf: ₹"&TEXT(Products!$I$39,"#,##0")&" sales, a loss of ₹"&TEXT(-Products!$J$39,"#,##0")&"." -> Furniture is 31% of sales but only 3.4% margin (₹56,785). Bookshelf: ₹432,523 sales, a loss of ₹22,877. | D7: Raise Bookshelf, Study Table and Shoe Rack prices or negotiate supplier cost; stop discounting Furniture beyond 10%. | E7: =-SUMIFS('Sales Data'!$R$2:$R$1201,'Sales Data'!$I$2:$I$1201,"Furniture",'Sales Data'!$R$2:$R$1201,"<0") -> 77802
A8: 3 | B8: A small set of products carries the business, and a few catalogue items barely sell. | C8: =COUNTIF(Products!$N$5:$N$44,"A")&" of "&COUNTIF(Products!$H$5:$H$44,">0")&" products sold are Class A and make "&TEXT(SUMIF(Products!$N$5:$N$44,"A",Products!$I$5:$I$44)/SUM(Products!$I$5:$I$44),"0.0%")&" of sales. Noise-Cancelling Headphones alone: "&TEXT(Products!$L$22,"0.0%")&" of sales, ₹"&TEXT(Products!$J$22,"#,##0")&" profit. "&COUNTIF(Products!$H$5:$H$44,"<10")&" products sold under 10 units." -> 13 of 38 products sold are Class A and make 79.2% of sales. Noise-Cancelling Headphones alone: 20.2% of sales, ₹275,057 profit. 4 products sold under 10 units. | D8: Never let Class A products run out of stock and negotiate supplier terms on them. Clear or delist the dead-stock items to free cash. | E8: =$C$14*SUMIF(Products!$N$5:$N$44,"A",Products!$J$5:$J$44) -> 37023.55
A9: 4 | B9: Sales peak in Q4 and fall hard after November; Q1 is the weakest quarter. | C9: ="Q4 is "&TEXT(Pivots!$K$27,"0.0%")&" of annual sales (₹"&TEXT(Pivots!$I$27,"#,##0")&"). November is the peak month (₹"&TEXT(Pivots!$D$34,"#,##0")&") and December falls "&TEXT(-(Pivots!$D$35-Pivots!$D$34)/Pivots!$D$34,"0.0%")&". Q1 sales: ₹"&TEXT(Pivots!$I$24,"#,##0")&"." -> Q4 is 36.5% of annual sales (₹1,978,359). November is the peak month (₹776,952) and December falls 31.4%. Q1 sales: ₹915,428. | D9: Build stock and ad budget before October. Run a loyalty or clearance push in December to Q1 so the dip is shallower. | E9: =$C$15*Pivots!$J$24 -> 18040.8
A10: 5 | B10: A minority of Champion customers produces most of the sales, and a sizeable At Risk group is slipping away. | C10: =COUNTIF(Customers!$N$5:$N$224,"Champion")&" Champions ("&TEXT(COUNTIF(Customers!$N$5:$N$224,"Champion")/COUNTA(Customers!$A$5:$A$224),"0%")&" of customers) generate "&TEXT('4 RFM Tasks'!$C$13,"0.0%")&" of sales. "&COUNTIF(Customers!$N$5:$N$224,"At Risk")&" At Risk customers have spent ₹"&TEXT(SUMIF(Customers!$N$5:$N$224,"At Risk",Customers!$I$5:$I$224),"#,##0")&"." -> 67 Champions (30% of customers) generate 62.6% of sales. 56 At Risk customers have spent ₹457,582. | D10: Launch a VIP programme (early access, free shipping) for Champions and a win-back offer for At Risk customers. | E10: =$C$16*SUMIF(Customers!$N$5:$N$224,"At Risk",Customers!$I$5:$I$224)*SUM('Sales Data'!$R$2:$R$1201)/SUM('Sales Data'!$P$2:$P$1201) -> 20446.833
B13: Assumptions behind the impact estimates (blue = editable input)
B14: Sales uplift on Class A products | C14: 0.05
B15: Sales uplift in the weakest quarter (Jan to Mar) | C15: 0.1
B16: Share of At Risk customers' annual spend won back | C16: 0.2
B17: All impacts are profit estimates in ₹. Finding 1 is the loss avoided by not selling above 20% discount (a floor: it ignores extra profit if customers still buy at 20%). Finding 2 is the total loss on loss-making Furniture orders. Findings 3 to 5 use the assumptions above, other factors held constant.

Sheet Answer Key
A1: Answer Key
A2: Open this only after you have finished. Expected answers are live formulas; the text shows what to type. Your answers are pulled in and marked.
A3: Score | B3: =SUM(E5:E64)&" out of 44" -> 44 out of 44
A5: 1 Clean Check
A6: Q | B6: How to get it | C6: Expected answer | D6: Your answer | E6: Match (1 = correct)
A7: CC1 | B7: Row count in the combined query before Remove Duplicates | C7: =COUNTA('Sales Data'!$A$2:$A$1201)+Helpers!$B$6 -> 1210 | D7: =IF('1 Clean Check'!C5="","",'1 Clean Check'!C5) -> 1210 | E7: =IF(D7="","",IF(ISNUMBER(C7),IF(ISNUMBER(D7),IF(ABS(D7-C7)<=IF(ABS(C7)<=1,0.005,0.5),1,0),0),IF(UPPER(TRIM(D7))=UPPER(TRIM(C7)),1,0))) -> 1
A8: CC2 | B8: Row count before minus row count after Remove Duplicates | C8: =Helpers!$B$6 -> 10 | D8: =IF('1 Clean Check'!C6="","",'1 Clean Check'!C6) -> 10 | E8: =IF(D8="","",IF(ISNUMBER(C8),IF(ISNUMBER(D8),IF(ABS(D8-C8)<=IF(ABS(C8)<=1,0.005,0.5),1,0),0),IF(UPPER(TRIM(D8))=UPPER(TRIM(C8)),1,0))) -> 1
A9: CC3 | B9: Row count of the final Sales_Clean table | C9: =COUNTA('Sales Data'!$A$2:$A$1201) -> 1200 | D9: =IF('1 Clean Check'!C7="","",'1 Clean Check'!C7) -> 1200 | E9: =IF(D9="","",IF(ISNUMBER(C9),IF(ISNUMBER(D9),IF(ABS(D9-C9)<=IF(ABS(C9)<=1,0.005,0.5),1,0),0),IF(UPPER(TRIM(D9))=UPPER(TRIM(C9)),1,0))) -> 1
A10: CC4 | B10: Sum of the Sales (₹) column of Sales_Clean | C10: =SUM('Sales Data'!$P$2:$P$1201) -> 5426671 | D10: =IF('1 Clean Check'!C8="","",'1 Clean Check'!C8) -> 5426671 | E10: =IF(D10="","",IF(ISNUMBER(C10),IF(ISNUMBER(D10),IF(ABS(D10-C10)<=IF(ABS(C10)<=1,0.005,0.5),1,0),0),IF(UPPER(TRIM(D10))=UPPER(TRIM(C10)),1,0))) -> 1
A11: CC5 | B11: Group By Customer Name and count rows in the result | C11: =COUNTA(Customers!$B$5:$B$224) -> 220 | D11: =IF('1 Clean Check'!C9="","",'1 Clean Check'!C9) -> 220 | E11: =IF(D11="","",IF(ISNUMBER(C11),IF(ISNUMBER(D11),IF(ABS(D11-C11)<=IF(ABS(C11)<=1,0.005,0.5),1,0),0),IF(UPPER(TRIM(D11))=UPPER(TRIM(C11)),1,0))) -> 1
A12: CC6 | B12: Group By Region and count rows in the result | C12: =ROUND(SUMPRODUCT(1/COUNTIF('Sales Data'!$G$2:$G$1201,'Sales Data'!$G$2:$G$1201)),0) -> 4 | D12: =IF('1 Clean Check'!C10="","",'1 Clean Check'!C10) -> 4 | E12: =IF(D12="","",IF(ISNUMBER(C12),IF(ISNUMBER(D12),IF(ABS(D12-C12)<=IF(ABS(C12)<=1,0.005,0.5),1,0),0),IF(UPPER(TRIM(D12))=UPPER(TRIM(C12)),1,0))) -> 1
A13: CC7 | B13: Filter Returned = Y and read the row count | C13: =COUNTIF('Sales Data'!$S$2:$S$1201,"Y") -> 48 | D13: =IF('1 Clean Check'!C11="","",'1 Clean Check'!C11) -> 48 | E13: =IF(D13="","",IF(ISNUMBER(C13),IF(ISNUMBER(D13),IF(ABS(D13-C13)<=IF(ABS(C13)<=1,0.005,0.5),1,0),0),IF(UPPER(TRIM(D13))=UPPER(TRIM(C13)),1,0))) -> 1
A15: 2 KPI Tasks
A16: Q | B16: Formula to type | C16: Expected answer | D16: Your answer | E16: Match (1 = correct)
A17: K1 | B17: =SUM(P2:P1201) | C17: =SUM('Sales Data'!$P$2:$P$1201) -> 5426671 | D17: =IF('2 KPI Tasks'!C5="","",'2 KPI Tasks'!C5) -> 5426671 | E17: =IF(D17="","",IF(ISNUMBER(C17),IF(ISNUMBER(D17),IF(ABS(D17-C17)<=IF(ABS(C17)<=1,0.005,0.5),1,0),0),IF(UPPER(TRIM(D17))=UPPER(TRIM(C17)),1,0))) -> 1
A18: K2 | B18: =SUM(R2:R1201) | C18: =SUM('Sales Data'!$R$2:$R$1201) -> 1212441 | D18: =IF('2 KPI Tasks'!C6="","",'2 KPI Tasks'!C6) -> 1212441 | E18: =IF(D18="","",IF(ISNUMBER(C18),IF(ISNUMBER(D18),IF(ABS(D18-C18)<=IF(ABS(C18)<=1,0.005,0.5),1,0),0),IF(UPPER(TRIM(D18))=UPPER(TRIM(C18)),1,0))) -> 1
A19: K3 | B19: =SUM(R2:R1201)/SUM(P2:P1201) | C19: =SUM('Sales Data'!$R$2:$R$1201)/SUM('Sales Data'!$P$2:$P$1201) -> 0.22342261 | D19: =IF('2 KPI Tasks'!C7="","",'2 KPI Tasks'!C7) -> 0.22342261 | E19: =IF(D19="","",IF(ISNUMBER(C19),IF(ISNUMBER(D19),IF(ABS(D19-C19)<=IF(ABS(C19)<=1,0.005,0.5),1,0),0),IF(UPPER(TRIM(D19))=UPPER(TRIM(C19)),1,0))) -> 1
A20: K4 | B20: =COUNTA(A2:A1201) | C20: =COUNTA('Sales Data'!$A$2:$A$1201) -> 1200 | D20: =IF('2 KPI Tasks'!C8="","",'2 KPI Tasks'!C8) -> 1200 | E20: =IF(D20="","",IF(ISNUMBER(C20),IF(ISNUMBER(D20),IF(ABS(D20-C20)<=IF(ABS(C20)<=1,0.005,0.5),1,0),0),IF(UPPER(TRIM(D20))=UPPER(TRIM(C20)),1,0))) -> 1
A21: K5 | B21: =SUM(P2:P1201)/COUNTA(A2:A1201) | C21: =SUM('Sales Data'!$P$2:$P$1201)/COUNTA('Sales Data'!$A$2:$A$1201) -> 4522.2258 | D21: =IF('2 KPI Tasks'!C9="","",'2 KPI Tasks'!C9) -> 4522.2258 | E21: =IF(D21="","",IF(ISNUMBER(C21),IF(ISNUMBER(D21),IF(ABS(D21-C21)<=IF(ABS(C21)<=1,0.005,0.5),1,0),0),IF(UPPER(TRIM(D21))=UPPER(TRIM(C21)),1,0))) -> 1
A22: K6 | B22: =COUNTIF(S2:S1201,"Y")/COUNTA(A2:A1201) | C22: =COUNTIF('Sales Data'!$S$2:$S$1201,"Y")/COUNTA('Sales Data'!$A$2:$A$1201) -> 0.04 | D22: =IF('2 KPI Tasks'!C10="","",'2 KPI Tasks'!C10) -> 0.04 | E22: =IF(D22="","",IF(ISNUMBER(C22),IF(ISNUMBER(D22),IF(ABS(D22-C22)<=IF(ABS(C22)<=1,0.005,0.5),1,0),0),IF(UPPER(TRIM(D22))=UPPER(TRIM(C22)),1,0))) -> 1
A23: K7 | B23: Pivot: Order Date grouped by Months, Sum of Sales, largest month or SUMPRODUCT((MONTH(B2:B1201)=n)*P2:P1201) for n = 1 to 12 | C23: =INDEX(Helpers!$B$11:$B$22,MATCH(MAX(Helpers!$C$11:$C$22),Helpers!$C$11:$C$22,0)) -> November | D23: =IF('2 KPI Tasks'!C11="","",'2 KPI Tasks'!C11) -> November | E23: =IF(D23="","",IF(ISNUMBER(C23),IF(ISNUMBER(D23),IF(ABS(D23-C23)<=IF(ABS(C23)<=1,0.005,0.5),1,0),0),IF(UPPER(TRIM(D23))=UPPER(TRIM(C23)),1,0))) -> 1
A24: K8 | B24: =(December Sales - November Sales)/November Sales | C24: =(Helpers!$C$22-Helpers!$C$21)/Helpers!$C$21 -> -0.31373624 | D24: =IF('2 KPI Tasks'!C12="","",'2 KPI Tasks'!C12) -> -0.31373624 | E24: =IF(D24="","",IF(ISNUMBER(C24),IF(ISNUMBER(D24),IF(ABS(D24-C24)<=IF(ABS(C24)<=1,0.005,0.5),1,0),0),IF(UPPER(TRIM(D24))=UPPER(TRIM(C24)),1,0))) -> 1
A25: K9 | B25: =SUMIFS(P2:P1201,G2:G1201,"West",O2:O1201,">=0.2") | C25: =SUMIFS('Sales Data'!$P$2:$P$1201,'Sales Data'!$G$2:$G$1201,"West",'Sales Data'!$O$2:$O$1201,">=0.2") -> 698690 | D25: =IF('2 KPI Tasks'!C13="","",'2 KPI Tasks'!C13) -> 698690 | E25: =IF(D25="","",IF(ISNUMBER(C25),IF(ISNUMBER(D25),IF(ABS(D25-C25)<=IF(ABS(C25)<=1,0.005,0.5),1,0),0),IF(UPPER(TRIM(D25))=UPPER(TRIM(C25)),1,0))) -> 1
A26: K10 | B26: =COUNTIF(R2:R1201,"<0") | C26: =COUNTIF('Sales Data'!$R$2:$R$1201,"<0") -> 92 | D26: =IF('2 KPI Tasks'!C14="","",'2 KPI Tasks'!C14) -> 92 | E26: =IF(D26="","",IF(ISNUMBER(C26),IF(ISNUMBER(D26),IF(ABS(D26-C26)<=IF(ABS(C26)<=1,0.005,0.5),1,0),0),IF(UPPER(TRIM(D26))=UPPER(TRIM(C26)),1,0))) -> 1
A27: K11 | B27: =-SUMIF(R2:R1201,"<0") | C27: =-SUMIF('Sales Data'!$R$2:$R$1201,"<0") -> 85926 | D27: =IF('2 KPI Tasks'!C15="","",'2 KPI Tasks'!C15) -> 85926 | E27: =IF(D27="","",IF(ISNUMBER(C27),IF(ISNUMBER(D27),IF(ABS(D27-C27)<=IF(ABS(C27)<=1,0.005,0.5),1,0),0),IF(UPPER(TRIM(D27))=UPPER(TRIM(C27)),1,0))) -> 1
A28: K12 | B28: =ROUND(SUMPRODUCT(C2:C1201-B2:B1201)/COUNTA(A2:A1201),2) | C28: =ROUND(SUMPRODUCT('Sales Data'!$C$2:$C$1201-'Sales Data'!$B$2:$B$1201)/COUNTA('Sales Data'!$A$2:$A$1201),2) -> 4 | D28: =IF('2 KPI Tasks'!C16="","",'2 KPI Tasks'!C16) -> 4 | E28: =IF(D28="","",IF(ISNUMBER(C28),IF(ISNUMBER(D28),IF(ABS(D28-C28)<=IF(ABS(C28)<=1,0.005,0.5),1,0),0),IF(UPPER(TRIM(D28))=UPPER(TRIM(C28)),1,0))) -> 1
A30: 3 ABC Tasks
A31: Q | B31: Formula to type | C31: Expected answer | D31: Your answer | E31: Match (1 = correct)
A32: A1 | B32: H5: =SUMIFS('Sales Data'!$M$2:$M$1201,'Sales Data'!$K$2:$K$1201,A5) I5: =SUMIFS('Sales Data'!$P$2:$P$1201,'Sales Data'!$K$2:$K$1201,A5) J5: =SUMIFS('Sales Data'!$R$2:$R$1201,'Sales Data'!$K$2:$K$1201,A5) then =SUM(I5:I44) | C32: =SUM(Helpers!$C$59:$C$98) -> 5426671 | D32: =IF('3 ABC Tasks'!C5="","",'3 ABC Tasks'!C5) -> 5426671 | E32: =IF(D32="","",IF(ISNUMBER(C32),IF(ISNUMBER(D32),IF(ABS(D32-C32)<=IF(ABS(C32)<=1,0.005,0.5),1,0),0),IF(UPPER(TRIM(D32))=UPPER(TRIM(C32)),1,0))) -> 1
A33: A2 | B33: =INDEX(B5:B44,MATCH(MAX(I5:I44),I5:I44,0)) | C33: =INDEX(Products!$B$5:$B$44,MATCH(MAX(Helpers!$C$59:$C$98),Helpers!$C$59:$C$98,0)) -> Noise-Cancelling Headphones | D33: =IF('3 ABC Tasks'!C6="","",'3 ABC Tasks'!C6) -> Noise-Cancelling Headphones | E33: =IF(D33="","",IF(ISNUMBER(C33),IF(ISNUMBER(D33),IF(ABS(D33-C33)<=IF(ABS(C33)<=1,0.005,0.5),1,0),0),IF(UPPER(TRIM(D33))=UPPER(TRIM(C33)),1,0))) -> 1
A34: A3 | B34: =INDEX(B5:B44,MATCH(MAX(J5:J44),J5:J44,0)) | C34: =INDEX(Products!$B$5:$B$44,MATCH(MAX(Helpers!$D$59:$D$98),Helpers!$D$59:$D$98,0)) -> Noise-Cancelling Headphones | D34: =IF('3 ABC Tasks'!C7="","",'3 ABC Tasks'!C7) -> Noise-Cancelling Headphones | E34: =IF(D34="","",IF(ISNUMBER(C34),IF(ISNUMBER(D34),IF(ABS(D34-C34)<=IF(ABS(C34)<=1,0.005,0.5),1,0),0),IF(UPPER(TRIM(D34))=UPPER(TRIM(C34)),1,0))) -> 1
A35: A4 | B35: =COUNTIF(J5:J44,"<0") | C35: =COUNTIF(Helpers!$D$59:$D$98,"<0") -> 1 | D35: =IF('3 ABC Tasks'!C8="","",'3 ABC Tasks'!C8) -> 1 | E35: =IF(D35="","",IF(ISNUMBER(C35),IF(ISNUMBER(D35),IF(ABS(D35-C35)<=IF(ABS(C35)<=1,0.005,0.5),1,0),0),IF(UPPER(TRIM(D35))=UPPER(TRIM(C35)),1,0))) -> 1
A36: A5 | B36: K5: =J5/I5 L5: =I5/SUM($I$5:$I$44) M5: =SUMIF($I$5:$I$44,">="&I5)/SUM($I$5:$I$44) N5: =IF(M5<=0.8,"A",IF(M5<=0.95,"B","C")) then =COUNTIF(N5:N44,"A") | C36: =COUNTIF(Helpers!$H$59:$H$98,"A") -> 13 | D36: =IF('3 ABC Tasks'!C9="","",'3 ABC Tasks'!C9) -> 13 | E36: =IF(D36="","",IF(ISNUMBER(C36),IF(ISNUMBER(D36),IF(ABS(D36-C36)<=IF(ABS(C36)<=1,0.005,0.5),1,0),0),IF(UPPER(TRIM(D36))=UPPER(TRIM(C36)),1,0))) -> 1
A37: A6 | B37: =SUMIF(N5:N44,"A",I5:I44)/SUM(I5:I44) | C37: =SUMIF(Helpers!$H$59:$H$98,"A",Helpers!$C$59:$C$98)/SUM(Helpers!$C$59:$C$98) -> 0.7924713 | D37: =IF('3 ABC Tasks'!C10="","",'3 ABC Tasks'!C10) -> 0.7924713 | E37: =IF(D37="","",IF(ISNUMBER(C37),IF(ISNUMBER(D37),IF(ABS(D37-C37)<=IF(ABS(C37)<=1,0.005,0.5),1,0),0),IF(UPPER(TRIM(D37))=UPPER(TRIM(C37)),1,0))) -> 1
A38: A7 | B38: =COUNTIF(H5:H44,"<10") | C38: =COUNTIF(Helpers!$B$59:$B$98,"<10") -> 4 | D38: =IF('3 ABC Tasks'!C11="","",'3 ABC Tasks'!C11) -> 4 | E38: =IF(D38="","",IF(ISNUMBER(C38),IF(ISNUMBER(D38),IF(ABS(D38-C38)<=IF(ABS(C38)<=1,0.005,0.5),1,0),0),IF(UPPER(TRIM(D38))=UPPER(TRIM(C38)),1,0))) -> 1
A39: A8 | B39: Pivot: Rows = Category, Values = Sum of Profit and Sum of Sales, then Profit / Sales or =SUMIFS(profit)/SUMIFS(sales) per category | C39: =INDEX(Helpers!$A$27:$A$32,MATCH(MAX(Helpers!$D$27:$D$32),Helpers!$D$27:$D$32,0)) -> Beauty | D39: =IF('3 ABC Tasks'!C12="","",'3 ABC Tasks'!C12) -> Beauty | E39: =IF(D39="","",IF(ISNUMBER(C39),IF(ISNUMBER(D39),IF(ABS(D39-C39)<=IF(ABS(C39)<=1,0.005,0.5),1,0),0),IF(UPPER(TRIM(D39))=UPPER(TRIM(C39)),1,0))) -> 1
A40: A9 | B40: =SUMIFS(R2:R1201,I2:I1201,"Furniture") | C40: =SUMIFS('Sales Data'!$R$2:$R$1201,'Sales Data'!$I$2:$I$1201,"Furniture") -> 56785 | D40: =IF('3 ABC Tasks'!C13="","",'3 ABC Tasks'!C13) -> 56785 | E40: =IF(D40="","",IF(ISNUMBER(C40),IF(ISNUMBER(D40),IF(ABS(D40-C40)<=IF(ABS(C40)<=1,0.005,0.5),1,0),0),IF(UPPER(TRIM(D40))=UPPER(TRIM(C40)),1,0))) -> 1
A42: 4 RFM Tasks
A43: Q | B43: Formula to type | C43: Expected answer | D43: Your answer | E43: Match (1 = correct)
A44: R1 | B44: F5: =COUNTIF('Sales Data'!$D$2:$D$1201,A5) G5: =MAXIFS('Sales Data'!$B$2:$B$1201,'Sales Data'!$D$2:$D$1201,A5) H5: =$Q$4-G5 I5: =SUMIFS('Sales Data'!$P$2:$P$1201,'Sales Data'!$D$2:$D$1201,A5) then =COUNTIF(F5:F224,1) | C44: =COUNTIF(Helpers!$B$102:$B$321,1) -> 29 | D44: =IF('4 RFM Tasks'!C5="","",'4 RFM Tasks'!C5) -> 29 | E44: =IF(D44="","",IF(ISNUMBER(C44),IF(ISNUMBER(D44),IF(ABS(D44-C44)<=IF(ABS(C44)<=1,0.005,0.5),1,0),0),IF(UPPER(TRIM(D44))=UPPER(TRIM(C44)),1,0))) -> 1
A45: R2 | B45: =INDEX(A5:A224,MATCH(MAX(I5:I224),I5:I224,0)) | C45: =INDEX(Helpers!$A$102:$A$321,MATCH(MAX(Helpers!$E$102:$E$321),Helpers!$E$102:$E$321,0)) -> C166 | D45: =IF('4 RFM Tasks'!C6="","",'4 RFM Tasks'!C6) -> C166 | E45: =IF(D45="","",IF(ISNUMBER(C45),IF(ISNUMBER(D45),IF(ABS(D45-C45)<=IF(ABS(C45)<=1,0.005,0.5),1,0),0),IF(UPPER(TRIM(D45))=UPPER(TRIM(C45)),1,0))) -> 1
A46: R3 | B46: =MAX(F5:F224) | C46: =MAX(Helpers!$B$102:$B$321) -> 20 | D46: =IF('4 RFM Tasks'!C7="","",'4 RFM Tasks'!C7) -> 20 | E46: =IF(D46="","",IF(ISNUMBER(C46),IF(ISNUMBER(D46),IF(ABS(D46-C46)<=IF(ABS(C46)<=1,0.005,0.5),1,0),0),IF(UPPER(TRIM(D46))=UPPER(TRIM(C46)),1,0))) -> 1
A47: R4 | B47: J5: =INDEX($Q$7:$Q$9,MATCH(H5,$P$7:$P$9,1)) K5: =INDEX($Q$12:$Q$14,MATCH(F5,$P$12:$P$14,1)) L5: =INDEX($Q$17:$Q$19,MATCH(I5,$P$17:$P$19,1)) M5: =J5+K5+L5 N5: =INDEX($Q$22:$Q$25,MATCH(M5,$P$22:$P$25,1)) then =COUNTIF(N5:N224,"Champion") | C47: =COUNTIF(Helpers!$J$102:$J$321,"Champion") -> 67 | D47: =IF('4 RFM Tasks'!C8="","",'4 RFM Tasks'!C8) -> 67 | E47: =IF(D47="","",IF(ISNUMBER(C47),IF(ISNUMBER(D47),IF(ABS(D47-C47)<=IF(ABS(C47)<=1,0.005,0.5),1,0),0),IF(UPPER(TRIM(D47))=UPPER(TRIM(C47)),1,0))) -> 1
A48: R5 | B48: =COUNTIF(N5:N224,"Loyal") | C48: =COUNTIF(Helpers!$J$102:$J$321,"Loyal") -> 76 | D48: =IF('4 RFM Tasks'!C9="","",'4 RFM Tasks'!C9) -> 76 | E48: =IF(D48="","",IF(ISNUMBER(C48),IF(ISNUMBER(D48),IF(ABS(D48-C48)<=IF(ABS(C48)<=1,0.005,0.5),1,0),0),IF(UPPER(TRIM(D48))=UPPER(TRIM(C48)),1,0))) -> 1
A49: R6 | B49: =COUNTIF(N5:N224,"At Risk") | C49: =COUNTIF(Helpers!$J$102:$J$321,"At Risk") -> 56 | D49: =IF('4 RFM Tasks'!C10="","",'4 RFM Tasks'!C10) -> 56 | E49: =IF(D49="","",IF(ISNUMBER(C49),IF(ISNUMBER(D49),IF(ABS(D49-C49)<=IF(ABS(C49)<=1,0.005,0.5),1,0),0),IF(UPPER(TRIM(D49))=UPPER(TRIM(C49)),1,0))) -> 1
A50: R7 | B50: =COUNTIF(N5:N224,"Lost") | C50: =COUNTIF(Helpers!$J$102:$J$321,"Lost") -> 21 | D50: =IF('4 RFM Tasks'!C11="","",'4 RFM Tasks'!C11) -> 21 | E50: =IF(D50="","",IF(ISNUMBER(C50),IF(ISNUMBER(D50),IF(ABS(D50-C50)<=IF(ABS(C50)<=1,0.005,0.5),1,0),0),IF(UPPER(TRIM(D50))=UPPER(TRIM(C50)),1,0))) -> 1
A51: R8 | B51: =SUMIF(N5:N224,"Champion",I5:I224) | C51: =SUMIF(Helpers!$J$102:$J$321,"Champion",Helpers!$E$102:$E$321) -> 3394545 | D51: =IF('4 RFM Tasks'!C12="","",'4 RFM Tasks'!C12) -> 3394545 | E51: =IF(D51="","",IF(ISNUMBER(C51),IF(ISNUMBER(D51),IF(ABS(D51-C51)<=IF(ABS(C51)<=1,0.005,0.5),1,0),0),IF(UPPER(TRIM(D51))=UPPER(TRIM(C51)),1,0))) -> 1
A52: R9 | B52: =SUMIF(N5:N224,"Champion",I5:I224)/SUM(I5:I224) | C52: =SUMIF(Helpers!$J$102:$J$321,"Champion",Helpers!$E$102:$E$321)/SUM(Helpers!$E$102:$E$321) -> 0.62552991 | D52: =IF('4 RFM Tasks'!C13="","",'4 RFM Tasks'!C13) -> 0.62552991 | E52: =IF(D52="","",IF(ISNUMBER(C52),IF(ISNUMBER(D52),IF(ABS(D52-C52)<=IF(ABS(C52)<=1,0.005,0.5),1,0),0),IF(UPPER(TRIM(D52))=UPPER(TRIM(C52)),1,0))) -> 1
A54: 5 Dashboard Tasks (expected values)
A55: Q | B55: How to get it | C55: Expected answer | D55: Your answer | E55: Match (1 = correct)
A56: D1 | B56: Pivot: Rows = Region, Sum of Sales or =SUMIFS(P2:P1201,G2:G1201,"West") | C56: =SUMIFS('Sales Data'!$P$2:$P$1201,'Sales Data'!$G$2:$G$1201,"West") -> 2190302 | D56: =IF('5 Dashboard Tasks'!C5="","",'5 Dashboard Tasks'!C5) -> 2190302 | E56: =IF(D56="","",IF(ISNUMBER(C56),IF(ISNUMBER(D56),IF(ABS(D56-C56)<=IF(ABS(C56)<=1,0.005,0.5),1,0),0),IF(UPPER(TRIM(D56))=UPPER(TRIM(C56)),1,0))) -> 1
A57: D2 | B57: Pivot: Rows = Category, Columns = Region, Sum of Sales | C57: =SUMIFS('Sales Data'!$P$2:$P$1201,'Sales Data'!$I$2:$I$1201,"Electronics",'Sales Data'!$G$2:$G$1201,"South") -> 590693 | D57: =IF('5 Dashboard Tasks'!C6="","",'5 Dashboard Tasks'!C6) -> 590693 | E57: =IF(D57="","",IF(ISNUMBER(C57),IF(ISNUMBER(D57),IF(ABS(D57-C57)<=IF(ABS(C57)<=1,0.005,0.5),1,0),0),IF(UPPER(TRIM(D57))=UPPER(TRIM(C57)),1,0))) -> 1
A58: D3 | B58: Pivot: group Order Date by Months and Quarters, read Qtr4 | C58: =SUMIFS('Sales Data'!$P$2:$P$1201,'Sales Data'!$B$2:$B$1201,">="&DATE(2025,10,1),'Sales Data'!$B$2:$B$1201,"<="&DATE(2025,12,31)) -> 1978359 | D58: =IF('5 Dashboard Tasks'!C7="","",'5 Dashboard Tasks'!C7) -> 1978359 | E58: =IF(D58="","",IF(ISNUMBER(C58),IF(ISNUMBER(D58),IF(ABS(D58-C58)<=IF(ABS(C58)<=1,0.005,0.5),1,0),0),IF(UPPER(TRIM(D58))=UPPER(TRIM(C58)),1,0))) -> 1
A59: D4 | B59: Pivot: Rows = Sub-Category, Sum of Profit, sort Largest to Smallest | C59: =INDEX(Helpers!$A$36:$A$55,MATCH(MAX(Helpers!$B$36:$B$55),Helpers!$B$36:$B$55,0)) -> Audio | D59: =IF('5 Dashboard Tasks'!C8="","",'5 Dashboard Tasks'!C8) -> Audio | E59: =IF(D59="","",IF(ISNUMBER(C59),IF(ISNUMBER(D59),IF(ABS(D59-C59)<=IF(ABS(C59)<=1,0.005,0.5),1,0),0),IF(UPPER(TRIM(D59))=UPPER(TRIM(C59)),1,0))) -> 1
A60: D5 | B60: Value Field Settings > Show Values As > % of Grand Total (Sum of Profit by Category) | C60: =SUMIFS('Sales Data'!$R$2:$R$1201,'Sales Data'!$I$2:$I$1201,"Electronics")/SUM('Sales Data'!$R$2:$R$1201) -> 0.36928395 | D60: =IF('5 Dashboard Tasks'!C9="","",'5 Dashboard Tasks'!C9) -> 0.36928395 | E60: =IF(D60="","",IF(ISNUMBER(C60),IF(ISNUMBER(D60),IF(ABS(D60-C60)<=IF(ABS(C60)<=1,0.005,0.5),1,0),0),IF(UPPER(TRIM(D60))=UPPER(TRIM(C60)),1,0))) -> 1
A61: D6 | B61: PivotTable Analyze > Fields, Items & Sets > Calculated Field: =Profit/Sales | C61: =SUMIFS('Sales Data'!$R$2:$R$1201,'Sales Data'!$I$2:$I$1201,"Furniture")/SUMIFS('Sales Data'!$P$2:$P$1201,'Sales Data'!$I$2:$I$1201,"Furniture") -> 0.033960594 | D61: =IF('5 Dashboard Tasks'!C10="","",'5 Dashboard Tasks'!C10) -> 0.033960594 | E61: =IF(D61="","",IF(ISNUMBER(C61),IF(ISNUMBER(D61),IF(ABS(D61-C61)<=IF(ABS(C61)<=1,0.005,0.5),1,0),0),IF(UPPER(TRIM(D61))=UPPER(TRIM(C61)),1,0))) -> 1
A62: D7 | B62: Helper column: =IF(O2=0,"No discount",IF(O2<=0.2,"Up to 20%","Above 20%")), then pivot Sum of Profit | C62: =SUMIFS('Sales Data'!$R$2:$R$1201,'Sales Data'!$O$2:$O$1201,">0.2") -> -47109 | D62: =IF('5 Dashboard Tasks'!C11="","",'5 Dashboard Tasks'!C11) -> -47109 | E62: =IF(D62="","",IF(ISNUMBER(C62),IF(ISNUMBER(D62),IF(ABS(D62-C62)<=IF(ABS(C62)<=1,0.005,0.5),1,0),0),IF(UPPER(TRIM(D62))=UPPER(TRIM(C62)),1,0))) -> 1

Sheet Helpers
A1: Helpers
A2: Supporting calculations used by the Answer Key. Do not edit.
A4: Assumption
A5: Item | B5: Value | C5: Note
A6: Duplicate rows planted in the CSV files | B6: 10 | C6: Set when the CSV files were generated; used for Clean Check answers 1 and 2 only.
A9: Sales by month
A10: Month no. | B10: Month | C10: Sales (₹)
A11: 1 | B11: =TEXT(DATE(2025,A11,1),"mmmm") -> January | C11: =SUMPRODUCT((MONTH('Sales Data'!$B$2:$B$1201)=A11)*'Sales Data'!$P$2:$P$1201) -> 305327
A12: 2 | B12: =TEXT(DATE(2025,A12,1),"mmmm") -> February | C12: =SUMPRODUCT((MONTH('Sales Data'!$B$2:$B$1201)=A12)*'Sales Data'!$P$2:$P$1201) -> 310888
A13: 3 | B13: =TEXT(DATE(2025,A13,1),"mmmm") -> March | C13: =SUMPRODUCT((MONTH('Sales Data'!$B$2:$B$1201)=A13)*'Sales Data'!$P$2:$P$1201) -> 299213
A14: 4 | B14: =TEXT(DATE(2025,A14,1),"mmmm") -> April | C14: =SUMPRODUCT((MONTH('Sales Data'!$B$2:$B$1201)=A14)*'Sales Data'!$P$2:$P$1201) -> 424765
A15: 5 | B15: =TEXT(DATE(2025,A15,1),"mmmm") -> May | C15: =SUMPRODUCT((MONTH('Sales Data'!$B$2:$B$1201)=A15)*'Sales Data'!$P$2:$P$1201) -> 444324
A16: 6 | B16: =TEXT(DATE(2025,A16,1),"mmmm") -> June | C16: =SUMPRODUCT((MONTH('Sales Data'!$B$2:$B$1201)=A16)*'Sales Data'!$P$2:$P$1201) -> 498900
A17: 7 | B17: =TEXT(DATE(2025,A17,1),"mmmm") -> July | C17: =SUMPRODUCT((MONTH('Sales Data'!$B$2:$B$1201)=A17)*'Sales Data'!$P$2:$P$1201) -> 418685
A18: 8 | B18: =TEXT(DATE(2025,A18,1),"mmmm") -> August | C18: =SUMPRODUCT((MONTH('Sales Data'!$B$2:$B$1201)=A18)*'Sales Data'!$P$2:$P$1201) -> 379426
A19: 9 | B19: =TEXT(DATE(2025,A19,1),"mmmm") -> September | C19: =SUMPRODUCT((MONTH('Sales Data'!$B$2:$B$1201)=A19)*'Sales Data'!$P$2:$P$1201) -> 366784
A20: 10 | B20: =TEXT(DATE(2025,A20,1),"mmmm") -> October | C20: =SUMPRODUCT((MONTH('Sales Data'!$B$2:$B$1201)=A20)*'Sales Data'!$P$2:$P$1201) -> 668213
A21: 11 | B21: =TEXT(DATE(2025,A21,1),"mmmm") -> November | C21: =SUMPRODUCT((MONTH('Sales Data'!$B$2:$B$1201)=A21)*'Sales Data'!$P$2:$P$1201) -> 776952
A22: 12 | B22: =TEXT(DATE(2025,A22,1),"mmmm") -> December | C22: =SUMPRODUCT((MONTH('Sales Data'!$B$2:$B$1201)=A22)*'Sales Data'!$P$2:$P$1201) -> 533194
A25: Sales and profit by category
A26: Category | B26: Sales (₹) | C26: Profit (₹) | D26: Profit Margin
A27: Electronics | B27: =SUMIFS('Sales Data'!$P$2:$P$1201,'Sales Data'!$I$2:$I$1201,A27) -> 1668215 | C27: =SUMIFS('Sales Data'!$R$2:$R$1201,'Sales Data'!$I$2:$I$1201,A27) -> 447735 | D27: =C27/B27 -> 0.26839166
A28: Apparel | B28: =SUMIFS('Sales Data'!$P$2:$P$1201,'Sales Data'!$I$2:$I$1201,A28) -> 726031 | C28: =SUMIFS('Sales Data'!$R$2:$R$1201,'Sales Data'!$I$2:$I$1201,A28) -> 200041 | D28: =C28/B28 -> 0.2755268
A29: Home | B29: =SUMIFS('Sales Data'!$P$2:$P$1201,'Sales Data'!$I$2:$I$1201,A29) -> 819850 | C29: =SUMIFS('Sales Data'!$R$2:$R$1201,'Sales Data'!$I$2:$I$1201,A29) -> 256160 | D29: =C29/B29 -> 0.3124474
A30: Beauty | B30: =SUMIFS('Sales Data'!$P$2:$P$1201,'Sales Data'!$I$2:$I$1201,A30) -> 313904 | C30: =SUMIFS('Sales Data'!$R$2:$R$1201,'Sales Data'!$I$2:$I$1201,A30) -> 154704 | D30: =C30/B30 -> 0.49283857
A31: Stationery | B31: =SUMIFS('Sales Data'!$P$2:$P$1201,'Sales Data'!$I$2:$I$1201,A31) -> 226586 | C31: =SUMIFS('Sales Data'!$R$2:$R$1201,'Sales Data'!$I$2:$I$1201,A31) -> 97016 | D31: =C31/B31 -> 0.42816414
A32: Furniture | B32: =SUMIFS('Sales Data'!$P$2:$P$1201,'Sales Data'!$I$2:$I$1201,A32) -> 1672085 | C32: =SUMIFS('Sales Data'!$R$2:$R$1201,'Sales Data'!$I$2:$I$1201,A32) -> 56785 | D32: =C32/B32 -> 0.033960594
A34: Profit by sub-category
A35: Sub-Category | B35: Profit (₹)
A36: Audio | B36: =SUMIFS('Sales Data'!$R$2:$R$1201,'Sales Data'!$J$2:$J$1201,A36) -> 305967
A37: Wearables | B37: =SUMIFS('Sales Data'!$R$2:$R$1201,'Sales Data'!$J$2:$J$1201,A37) -> 49064
A38: Accessories | B38: =SUMIFS('Sales Data'!$R$2:$R$1201,'Sales Data'!$J$2:$J$1201,A38) -> 92704
A39: Topwear | B39: =SUMIFS('Sales Data'!$R$2:$R$1201,'Sales Data'!$J$2:$J$1201,A39) -> 26160
A40: Bottomwear | B40: =SUMIFS('Sales Data'!$R$2:$R$1201,'Sales Data'!$J$2:$J$1201,A40) -> 50622
A41: Bedding | B41: =SUMIFS('Sales Data'!$R$2:$R$1201,'Sales Data'!$J$2:$J$1201,A41) -> 30798
A42: Kitchen | B42: =SUMIFS('Sales Data'!$R$2:$R$1201,'Sales Data'!$J$2:$J$1201,A42) -> 142631
A43: Decor | B43: =SUMIFS('Sales Data'!$R$2:$R$1201,'Sales Data'!$J$2:$J$1201,A43) -> 82731
A44: Skincare | B44: =SUMIFS('Sales Data'!$R$2:$R$1201,'Sales Data'!$J$2:$J$1201,A44) -> 42913
A45: Fragrance | B45: =SUMIFS('Sales Data'!$R$2:$R$1201,'Sales Data'!$J$2:$J$1201,A45) -> 60437
A46: Paper | B46: =SUMIFS('Sales Data'!$R$2:$R$1201,'Sales Data'!$J$2:$J$1201,A46) -> 9604
A47: Writing | B47: =SUMIFS('Sales Data'!$R$2:$R$1201,'Sales Data'!$J$2:$J$1201,A47) -> 15135
... A55: Storage | B55: =SUMIFS('Sales Data'!$R$2:$R$1201,'Sales Data'!$J$2:$J$1201,A55) -> -9935
A57: Totals by product
A58: Product ID | B58: Units Sold | C58: Sales (₹) | D58: Profit (₹) | E58: Profit Margin | F58: Sales Share | G58: Cumulative Share | H58: ABC Class
A59: =Products!A5 -> P001 | B59: =SUMIFS('Sales Data'!$M$2:$M$1201,'Sales Data'!$K$2:$K$1201,A59) -> 10 | C59: =SUMIFS('Sales Data'!$P$2:$P$1201,'Sales Data'!$K$2:$K$1201,A59) -> 24240 | D59: =SUMIFS('Sales Data'!$R$2:$R$1201,'Sales Data'!$K$2:$K$1201,A59) -> 9240 | E59: =IF(C59=0,0,D59/C59) -> 0.38118812 | F59: =C59/SUM($C$59:$C$98) -> 0.0044668269 | G59: =SUMIF($C$59:$C$98,">="&C59)/SUM($C$59:$C$98) -> 0.97916421 | H59: =IF(G59<=0.8,"A",IF(G59<=0.95,"B","C")) -> C
A60: =Products!A6 -> P002 | B60: =SUMIFS('Sales Data'!$M$2:$M$1201,'Sales Data'!$K$2:$K$1201,A60) -> 37 | C60: =SUMIFS('Sales Data'!$P$2:$P$1201,'Sales Data'!$K$2:$K$1201,A60) -> 208164 | D60: =SUMIFS('Sales Data'!$R$2:$R$1201,'Sales Data'!$K$2:$K$1201,A60) -> 49064 | E60: =IF(C60=0,0,D60/C60) -> 0.23569878 | F60: =C60/SUM($C$59:$C$98) -> 0.038359429 | G60: =SUMIF($C$59:$C$98,">="&C60)/SUM($C$59:$C$98) -> 0.66130506 | H60: =IF(G60<=0.8,"A",IF(G60<=0.95,"B","C")) -> A
A61: =Products!A7 -> P003 | B61: =SUMIFS('Sales Data'!$M$2:$M$1201,'Sales Data'!$K$2:$K$1201,A61) -> 23 | C61: =SUMIFS('Sales Data'!$P$2:$P$1201,'Sales Data'!$K$2:$K$1201,A61) -> 31852 | D61: =SUMIFS('Sales Data'!$R$2:$R$1201,'Sales Data'!$K$2:$K$1201,A61) -> 11152 | E61: =IF(C61=0,0,D61/C61) -> 0.3501193 | F61: =C61/SUM($C$59:$C$98) -> 0.0058695285 | G61: =SUMIF($C$59:$C$98,">="&C61)/SUM($C$59:$C$98) -> 0.96475906 | H61: =IF(G61<=0.8,"A",IF(G61<=0.95,"B","C")) -> C
A62: =Products!A8 -> P004 | B62: =SUMIFS('Sales Data'!$M$2:$M$1201,'Sales Data'!$K$2:$K$1201,A62) -> 20 | C62: =SUMIFS('Sales Data'!$P$2:$P$1201,'Sales Data'!$K$2:$K$1201,A62) -> 63670 | D62: =SUMIFS('Sales Data'!$R$2:$R$1201,'Sales Data'!$K$2:$K$1201,A62) -> 21670 | E62: =IF(C62=0,0,D62/C62) -> 0.34034867 | F62: =C62/SUM($C$59:$C$98) -> 0.011732792 | G62: =SUMIF($C$59:$C$98,">="&C62)/SUM($C$59:$C$98) -> 0.90846635 | H62: =IF(G62<=0.8,"A",IF(G62<=0.95,"B","C")) -> B
A63: =Products!A9 -> P005 | B63: =SUMIFS('Sales Data'!$M$2:$M$1201,'Sales Data'!$K$2:$K$1201,A63) -> 13 | C63: =SUMIFS('Sales Data'!$P$2:$P$1201,'Sales Data'!$K$2:$K$1201,A63) -> 7830 | D63: =SUMIFS('Sales Data'!$R$2:$R$1201,'Sales Data'!$K$2:$K$1201,A63) -> 2890 | E63: =IF(C63=0,0,D63/C63) -> 0.36909323 | F63: =C63/SUM($C$59:$C$98) -> 0.0014428735 | G63: =SUMIF($C$59:$C$98,">="&C63)/SUM($C$59:$C$98) -> 0.99968544 | H63: =IF(G63<=0.8,"A",IF(G63<=0.95,"B","C")) -> C
A64: =Products!A10 -> P006 | B64: =SUMIFS('Sales Data'!$M$2:$M$1201,'Sales Data'!$K$2:$K$1201,A64) -> 85 | C64: =SUMIFS('Sales Data'!$P$2:$P$1201,'Sales Data'!$K$2:$K$1201,A64) -> 131131 | D64: =SUMIFS('Sales Data'!$R$2:$R$1201,'Sales Data'!$K$2:$K$1201,A64) -> 41881 | E64: =IF(C64=0,0,D64/C64) -> 0.31938291 | F64: =C64/SUM($C$59:$C$98) -> 0.02416417 | G64: =SUMIF($C$59:$C$98,">="&C64)/SUM($C$59:$C$98) -> 0.7924713 | H64: =IF(G64<=0.8,"A",IF(G64<=0.95,"B","C")) -> A
A65: =Products!A11 -> P007 | B65: =SUMIFS('Sales Data'!$M$2:$M$1201,'Sales Data'!$K$2:$K$1201,A65) -> 36 | C65: =SUMIFS('Sales Data'!$P$2:$P$1201,'Sales Data'!$K$2:$K$1201,A65) -> 53429 | D65: =SUMIFS('Sales Data'!$R$2:$R$1201,'Sales Data'!$K$2:$K$1201,A65) -> 19229 | E65: =IF(C65=0,0,D65/C65) -> 0.35989818 | F65: =C65/SUM($C$59:$C$98) -> 0.009845631 | G65: =SUMIF($C$59:$C$98,">="&C65)/SUM($C$59:$C$98) -> 0.92878765 | H65: =IF(G65<=0.8,"A",IF(G65<=0.95,"B","C")) -> B
A66: =Products!A12 -> P008 | B66: =SUMIFS('Sales Data'!$M$2:$M$1201,'Sales Data'!$K$2:$K$1201,A66) -> 64 | C66: =SUMIFS('Sales Data'!$P$2:$P$1201,'Sales Data'!$K$2:$K$1201,A66) -> 75598 | D66: =SUMIFS('Sales Data'!$R$2:$R$1201,'Sales Data'!$K$2:$K$1201,A66) -> 30798 | E66: =IF(C66=0,0,D66/C66) -> 0.40739173 | F66: =C66/SUM($C$59:$C$98) -> 0.013930824 | G66: =SUMIF($C$59:$C$98,">="&C66)/SUM($C$59:$C$98) -> 0.89673356 | H66: =IF(G66<=0.8,"A",IF(G66<=0.95,"B","C")) -> B
A67: =Products!A13 -> P009 | B67: =SUMIFS('Sales Data'!$M$2:$M$1201,'Sales Data'!$K$2:$K$1201,A67) -> 105 | C67: =SUMIFS('Sales Data'!$P$2:$P$1201,'Sales Data'!$K$2:$K$1201,A67) -> 287750 | D67: =SUMIFS('Sales Data'!$R$2:$R$1201,'Sales Data'!$K$2:$K$1201,A67) -> 77750 | E67: =IF(C67=0,0,D67/C67) -> 0.27019983 | F67: =C67/SUM($C$59:$C$98) -> 0.053025142 | G67: =SUMIF($C$59:$C$98,">="&C67)/SUM($C$59:$C$98) -> 0.57233007 | H67: =IF(G67<=0.8,"A",IF(G67<=0.95,"B","C")) -> A
A68: =Products!A14 -> P010 | B68: =SUMIFS('Sales Data'!$M$2:$M$1201,'Sales Data'!$K$2:$K$1201,A68) -> 81 | C68: =SUMIFS('Sales Data'!$P$2:$P$1201,'Sales Data'!$K$2:$K$1201,A68) -> 75622 | D68: =SUMIFS('Sales Data'!$R$2:$R$1201,'Sales Data'!$K$2:$K$1201,A68) -> 33502 | E68: =IF(C68=0,0,D68/C68) -> 0.44301923 | F68: =C68/SUM($C$59:$C$98) -> 0.013935247 | G68: =SUMIF($C$59:$C$98,">="&C68)/SUM($C$59:$C$98) -> 0.88280273 | H68: =IF(G68<=0.8,"A",IF(G68<=0.95,"B","C")) -> B
A69: =Products!A15 -> P011 | B69: =SUMIFS('Sales Data'!$M$2:$M$1201,'Sales Data'!$K$2:$K$1201,A69) -> 63 | C69: =SUMIFS('Sales Data'!$P$2:$P$1201,'Sales Data'!$K$2:$K$1201,A69) -> 49487 | D69: =SUMIFS('Sales Data'!$R$2:$R$1201,'Sales Data'!$K$2:$K$1201,A69) -> 25547 | E69: =IF(C69=0,0,D69/C69) -> 0.51623659 | F69: =C69/SUM($C$59:$C$98) -> 0.0091192188 | G69: =SUMIF($C$59:$C$98,">="&C69)/SUM($C$59:$C$98) -> 0.93790687 | H69: =IF(G69<=0.8,"A",IF(G69<=0.95,"B","C")) -> B
A70: =Products!A16 -> P012 | B70: =SUMIFS('Sales Data'!$M$2:$M$1201,'Sales Data'!$K$2:$K$1201,A70) -> 92 | C70: =SUMIFS('Sales Data'!$P$2:$P$1201,'Sales Data'!$K$2:$K$1201,A70) -> 129437 | D70: =SUMIFS('Sales Data'!$R$2:$R$1201,'Sales Data'!$K$2:$K$1201,A70) -> 60437 | E70: =IF(C70=0,0,D70/C70) -> 0.46692213 | F70: =C70/SUM($C$59:$C$98) -> 0.023852008 | G70: =SUMIF($C$59:$C$98,">="&C70)/SUM($C$59:$C$98) -> 0.8163233 | H70: =IF(G70<=0.8,"A",IF(G70<=0.95,"B","C")) -> B
... A98: =Products!A44 -> P040 | B98: =SUMIFS('Sales Data'!$M$2:$M$1201,'Sales Data'!$K$2:$K$1201,A98) -> 3 | C98: =SUMIFS('Sales Data'!$P$2:$P$1201,'Sales Data'!$K$2:$K$1201,A98) -> 1707 | D98: =SUMIFS('Sales Data'!$R$2:$R$1201,'Sales Data'!$K$2:$K$1201,A98) -> 807 | E98: =IF(C98=0,0,D98/C98) -> 0.47275923 | F98: =C98/SUM($C$59:$C$98) -> 0.00031455749 | G98: =SUMIF($C$59:$C$98,">="&C98)/SUM($C$59:$C$98) -> 1 | H98: =IF(G98<=0.8,"A",IF(G98<=0.95,"B","C")) -> C
A100: Totals by customer
A101: Customer ID | B101: Orders | C101: Last Order Date | D101: Days Since Last Order | E101: Total Sales (₹) | F101: R Score | G101: F Score | H101: M Score | I101: Total Score | J101: RFM Segment
A102: =Customers!A5 -> C001 | B102: =COUNTIF('Sales Data'!$D$2:$D$1201,A102) -> 4 | C102: =_xlfn.MAXIFS('Sales Data'!$B$2:$B$1201,'Sales Data'!$D$2:$D$1201,A102) -> 45965 | D102: =Customers!$Q$4-C102 -> 57 | E102: =SUMIFS('Sales Data'!$P$2:$P$1201,'Sales Data'!$D$2:$D$1201,A102) -> 8654 | F102: =INDEX(Customers!$Q$7:$Q$9,MATCH(D102,Customers!$P$7:$P$9,1)) -> 2 | G102: =INDEX(Customers!$Q$12:$Q$14,MATCH(B102,Customers!$P$12:$P$14,1)) -> 2 | H102: =INDEX(Customers!$Q$17:$Q$19,MATCH(E102,Customers!$P$17:$P$19,1)) -> 1 | I102: =F102+G102+H102 -> 5 | J102: =INDEX(Customers!$Q$22:$Q$25,MATCH(I102,Customers!$P$22:$P$25,1)) -> At Risk
A103: =Customers!A6 -> C002 | B103: =COUNTIF('Sales Data'!$D$2:$D$1201,A103) -> 3 | C103: =_xlfn.MAXIFS('Sales Data'!$B$2:$B$1201,'Sales Data'!$D$2:$D$1201,A103) -> 45882 | D103: =Customers!$Q$4-C103 -> 140 | E103: =SUMIFS('Sales Data'!$P$2:$P$1201,'Sales Data'!$D$2:$D$1201,A103) -> 23645 | F103: =INDEX(Customers!$Q$7:$Q$9,MATCH(D103,Customers!$P$7:$P$9,1)) -> 2 | G103: =INDEX(Customers!$Q$12:$Q$14,MATCH(B103,Customers!$P$12:$P$14,1)) -> 2 | H103: =INDEX(Customers!$Q$17:$Q$19,MATCH(E103,Customers!$P$17:$P$19,1)) -> 2 | I103: =F103+G103+H103 -> 6 | J103: =INDEX(Customers!$Q$22:$Q$25,MATCH(I103,Customers!$P$22:$P$25,1)) -> Loyal
A104: =Customers!A7 -> C003 | B104: =COUNTIF('Sales Data'!$D$2:$D$1201,A104) -> 2 | C104: =_xlfn.MAXIFS('Sales Data'!$B$2:$B$1201,'Sales Data'!$D$2:$D$1201,A104) -> 45930 | D104: =Customers!$Q$4-C104 -> 92 | E104: =SUMIFS('Sales Data'!$P$2:$P$1201,'Sales Data'!$D$2:$D$1201,A104) -> 1420 | F104: =INDEX(Customers!$Q$7:$Q$9,MATCH(D104,Customers!$P$7:$P$9,1)) -> 2 | G104: =INDEX(Customers!$Q$12:$Q$14,MATCH(B104,Customers!$P$12:$P$14,1)) -> 1 | H104: =INDEX(Customers!$Q$17:$Q$19,MATCH(E104,Customers!$P$17:$P$19,1)) -> 1 | I104: =F104+G104+H104 -> 4 | J104: =INDEX(Customers!$Q$22:$Q$25,MATCH(I104,Customers!$P$22:$P$25,1)) -> At Risk
A105: =Customers!A8 -> C004 | B105: =COUNTIF('Sales Data'!$D$2:$D$1201,A105) -> 7 | C105: =_xlfn.MAXIFS('Sales Data'!$B$2:$B$1201,'Sales Data'!$D$2:$D$1201,A105) -> 46008 | D105: =Customers!$Q$4-C105 -> 14 | E105: =SUMIFS('Sales Data'!$P$2:$P$1201,'Sales Data'!$D$2:$D$1201,A105) -> 30772 | F105: =INDEX(Customers!$Q$7:$Q$9,MATCH(D105,Customers!$P$7:$P$9,1)) -> 3 | G105: =INDEX(Customers!$Q$12:$Q$14,MATCH(B105,Customers!$P$12:$P$14,1)) -> 3 | H105: =INDEX(Customers!$Q$17:$Q$19,MATCH(E105,Customers!$P$17:$P$19,1)) -> 2 | I105: =F105+G105+H105 -> 8 | J105: =INDEX(Customers!$Q$22:$Q$25,MATCH(I105,Customers!$P$22:$P$25,1)) -> Champion
A106: =Customers!A9 -> C005 | B106: =COUNTIF('Sales Data'!$D$2:$D$1201,A106) -> 2 | C106: =_xlfn.MAXIFS('Sales Data'!$B$2:$B$1201,'Sales Data'!$D$2:$D$1201,A106) -> 45983 | D106: =Customers!$Q$4-C106 -> 39 | E106: =SUMIFS('Sales Data'!$P$2:$P$1201,'Sales Data'!$D$2:$D$1201,A106) -> 4754 | F106: =INDEX(Customers!$Q$7:$Q$9,MATCH(D106,Customers!$P$7:$P$9,1)) -> 3 | G106: =INDEX(Customers!$Q$12:$Q$14,MATCH(B106,Customers!$P$12:$P$14,1)) -> 1 | H106: =INDEX(Customers!$Q$17:$Q$19,MATCH(E106,Customers!$P$17:$P$19,1)) -> 1 | I106: =F106+G106+H106 -> 5 | J106: =INDEX(Customers!$Q$22:$Q$25,MATCH(I106,Customers!$P$22:$P$25,1)) -> At Risk
A107: =Customers!A10 -> C006 | B107: =COUNTIF('Sales Data'!$D$2:$D$1201,A107) -> 6 | C107: =_xlfn.MAXIFS('Sales Data'!$B$2:$B$1201,'Sales Data'!$D$2:$D$1201,A107) -> 45999 | D107: =Customers!$Q$4-C107 -> 23 | E107: =SUMIFS('Sales Data'!$P$2:$P$1201,'Sales Data'!$D$2:$D$1201,A107) -> 20096 | F107: =INDEX(Customers!$Q$7:$Q$9,MATCH(D107,Customers!$P$7:$P$9,1)) -> 3 | G107: =INDEX(Customers!$Q$12:$Q$14,MATCH(B107,Customers!$P$12:$P$14,1)) -> 2 | H107: =INDEX(Customers!$Q$17:$Q$19,MATCH(E107,Customers!$P$17:$P$19,1)) -> 2 | I107: =F107+G107+H107 -> 7 | J107: =INDEX(Customers!$Q$22:$Q$25,MATCH(I107,Customers!$P$22:$P$25,1)) -> Loyal
A108: =Customers!A11 -> C007 | B108: =COUNTIF('Sales Data'!$D$2:$D$1201,A108) -> 2 | C108: =_xlfn.MAXIFS('Sales Data'!$B$2:$B$1201,'Sales Data'!$D$2:$D$1201,A108) -> 45866 | D108: =Customers!$Q$4-C108 -> 156 | E108: =SUMIFS('Sales Data'!$P$2:$P$1201,'Sales Data'!$D$2:$D$1201,A108) -> 3874 | F108: =INDEX(Customers!$Q$7:$Q$9,MATCH(D108,Customers!$P$7:$P$9,1)) -> 1 | G108: =INDEX(Customers!$Q$12:$Q$14,MATCH(B108,Customers!$P$12:$P$14,1)) -> 1 | H108: =INDEX(Customers!$Q$17:$Q$19,MATCH(E108,Customers!$P$17:$P$19,1)) -> 1 | I108: =F108+G108+H108 -> 3 | J108: =INDEX(Customers!$Q$22:$Q$25,MATCH(I108,Customers!$P$22:$P$25,1)) -> Lost
A109: =Customers!A12 -> C008 | B109: =COUNTIF('Sales Data'!$D$2:$D$1201,A109) -> 7 | C109: =_xlfn.MAXIFS('Sales Data'!$B$2:$B$1201,'Sales Data'!$D$2:$D$1201,A109) -> 45976 | D109: =Customers!$Q$4-C109 -> 46 | E109: =SUMIFS('Sales Data'!$P$2:$P$1201,'Sales Data'!$D$2:$D$1201,A109) -> 17849 | F109: =INDEX(Customers!$Q$7:$Q$9,MATCH(D109,Customers!$P$7:$P$9,1)) -> 2 | G109: =INDEX(Customers!$Q$12:$Q$14,MATCH(B109,Customers!$P$12:$P$14,1)) -> 3 | H109: =INDEX(Customers!$Q$17:$Q$19,MATCH(E109,Customers!$P$17:$P$19,1)) -> 2 | I109: =F109+G109+H109 -> 7 | J109: =INDEX(Customers!$Q$22:$Q$25,MATCH(I109,Customers!$P$22:$P$25,1)) -> Loyal
A110: =Customers!A13 -> C009 | B110: =COUNTIF('Sales Data'!$D$2:$D$1201,A110) -> 4 | C110: =_xlfn.MAXIFS('Sales Data'!$B$2:$B$1201,'Sales Data'!$D$2:$D$1201,A110) -> 45965 | D110: =Customers!$Q$4-C110 -> 57 | E110: =SUMIFS('Sales Data'!$P$2:$P$1201,'Sales Data'!$D$2:$D$1201,A110) -> 12094 | F110: =INDEX(Customers!$Q$7:$Q$9,MATCH(D110,Customers!$P$7:$P$9,1)) -> 2 | G110: =INDEX(Customers!$Q$12:$Q$14,MATCH(B110,Customers!$P$12:$P$14,1)) -> 2 | H110: =INDEX(Customers!$Q$17:$Q$19,MATCH(E110,Customers!$P$17:$P$19,1)) -> 2 | I110: =F110+G110+H110 -> 6 | J110: =INDEX(Customers!$Q$22:$Q$25,MATCH(I110,Customers!$P$22:$P$25,1)) -> Loyal
A111: =Customers!A14 -> C010 | B111: =COUNTIF('Sales Data'!$D$2:$D$1201,A111) -> 3 | C111: =_xlfn.MAXIFS('Sales Data'!$B$2:$B$1201,'Sales Data'!$D$2:$D$1201,A111) -> 45983 | D111: =Customers!$Q$4-C111 -> 39 | E111: =SUMIFS('Sales Data'!$P$2:$P$1201,'Sales Data'!$D$2:$D$1201,A111) -> 15734 | F111: =INDEX(Customers!$Q$7:$Q$9,MATCH(D111,Customers!$P$7:$P$9,1)) -> 3 | G111: =INDEX(Customers!$Q$12:$Q$14,MATCH(B111,Customers!$P$12:$P$14,1)) -> 2 | H111: =INDEX(Customers!$Q$17:$Q$19,MATCH(E111,Customers!$P$17:$P$19,1)) -> 2 | I111: =F111+G111+H111 -> 7 | J111: =INDEX(Customers!$Q$22:$Q$25,MATCH(I111,Customers!$P$22:$P$25,1)) -> Loyal
A112: =Customers!A15 -> C011 | B112: =COUNTIF('Sales Data'!$D$2:$D$1201,A112) -> 2 | C112: =_xlfn.MAXIFS('Sales Data'!$B$2:$B$1201,'Sales Data'!$D$2:$D$1201,A112) -> 45953 | D112: =Customers!$Q$4-C112 -> 69 | E112: =SUMIFS('Sales Data'!$P$2:$P$1201,'Sales Data'!$D$2:$D$1201,A112) -> 4123 | F112: =INDEX(Customers!$Q$7:$Q$9,MATCH(D112,Customers!$P$7:$P$9,1)) -> 2 | G112: =INDEX(Customers!$Q$12:$Q$14,MATCH(B112,Customers!$P$12:$P$14,1)) -> 1 | H112: =INDEX(Customers!$Q$17:$Q$19,MATCH(E112,Customers!$P$17:$P$19,1)) -> 1 | I112: =F112+G112+H112 -> 4 | J112: =INDEX(Customers!$Q$22:$Q$25,MATCH(I112,Customers!$P$22:$P$25,1)) -> At Risk
A113: =Customers!A16 -> C012 | B113: =COUNTIF('Sales Data'!$D$2:$D$1201,A113) -> 15 | C113: =_xlfn.MAXIFS('Sales Data'!$B$2:$B$1201,'Sales Data'!$D$2:$D$1201,A113) -> 46012 | D113: =Customers!$Q$4-C113 -> 10 | E113: =SUMIFS('Sales Data'!$P$2:$P$1201,'Sales Data'!$D$2:$D$1201,A113) -> 80674 | F113: =INDEX(Customers!$Q$7:$Q$9,MATCH(D113,Customers!$P$7:$P$9,1)) -> 3 | G113: =INDEX(Customers!$Q$12:$Q$14,MATCH(B113,Customers!$P$12:$P$14,1)) -> 3 | H113: =INDEX(Customers!$Q$17:$Q$19,MATCH(E113,Customers!$P$17:$P$19,1)) -> 3 | I113: =F113+G113+H113 -> 9 | J113: =INDEX(Customers!$Q$22:$Q$25,MATCH(I113,Customers!$P$22:$P$25,1)) -> Champion
... A321: =Customers!A224 -> C220 | B321: =COUNTIF('Sales Data'!$D$2:$D$1201,A321) -> 2 | C321: =_xlfn.MAXIFS('Sales Data'!$B$2:$B$1201,'Sales Data'!$D$2:$D$1201,A321) -> 45891 | D321: =Customers!$Q$4-C321 -> 131 | E321: =SUMIFS('Sales Data'!$P$2:$P$1201,'Sales Data'!$D$2:$D$1201,A321) -> 2846 | F321: =INDEX(Customers!$Q$7:$Q$9,MATCH(D321,Customers!$P$7:$P$9,1)) -> 2 | G321: =INDEX(Customers!$Q$12:$Q$14,MATCH(B321,Customers!$P$12:$P$14,1)) -> 1 | H321: =INDEX(Customers!$Q$17:$Q$19,MATCH(E321,Customers!$P$17:$P$19,1)) -> 1 | I321: =F321+G321+H321 -> 4 | J321: =INDEX(Customers!$Q$22:$Q$25,MATCH(I321,Customers!$P$22:$P$25,1)) -> At Risk

Sheet Dash_Calc
A1: Dashboard calculations (chart data, driven by the filters on the Dashboard sheet). Do not edit.
A3: Region criterion | B3: =IF(Dashboard!$C$5="All","*",Dashboard!$C$5) -> *
A4: Category criterion | B4: =IF(Dashboard!$E$5="All","*",Dashboard!$E$5) -> *
A5: From date | B5: =Dashboard!$G$5 -> 45658
A6: To date | B6: =Dashboard!$I$5 -> 46022
A9: Month start | B9: Month | C9: Sales (₹) | D9: Profit (₹)
A10: =DATE(2025,1,1) -> 45658 | B10: =TEXT(A10,"mmm") -> Jan | C10: =SUMIFS('Sales Data'!$P$2:$P$1201,'Sales Data'!$G$2:$G$1201,$B$3,'Sales Data'!$I$2:$I$1201,$B$4,'Sales Data'!$B$2:$B$1201,">="&MAX(A10,$B$5),'Sales Data'!$B$2:$B$1201,"<="&MIN(EOMONTH(A10,0),$B$6)) -> 305327 | D10: =SUMIFS('Sales Data'!$R$2:$R$1201,'Sales Data'!$G$2:$G$1201,$B$3,'Sales Data'!$I$2:$I$1201,$B$4,'Sales Data'!$B$2:$B$1201,">="&MAX(A10,$B$5),'Sales Data'!$B$2:$B$1201,"<="&MIN(EOMONTH(A10,0),$B$6)) -> 78507
A11: =DATE(2025,2,1) -> 45689 | B11: =TEXT(A11,"mmm") -> Feb | C11: =SUMIFS('Sales Data'!$P$2:$P$1201,'Sales Data'!$G$2:$G$1201,$B$3,'Sales Data'!$I$2:$I$1201,$B$4,'Sales Data'!$B$2:$B$1201,">="&MAX(A11,$B$5),'Sales Data'!$B$2:$B$1201,"<="&MIN(EOMONTH(A11,0),$B$6)) -> 310888 | D11: =SUMIFS('Sales Data'!$R$2:$R$1201,'Sales Data'!$G$2:$G$1201,$B$3,'Sales Data'!$I$2:$I$1201,$B$4,'Sales Data'!$B$2:$B$1201,">="&MAX(A11,$B$5),'Sales Data'!$B$2:$B$1201,"<="&MIN(EOMONTH(A11,0),$B$6)) -> 47508
A12: =DATE(2025,3,1) -> 45717 | B12: =TEXT(A12,"mmm") -> Mar | C12: =SUMIFS('Sales Data'!$P$2:$P$1201,'Sales Data'!$G$2:$G$1201,$B$3,'Sales Data'!$I$2:$I$1201,$B$4,'Sales Data'!$B$2:$B$1201,">="&MAX(A12,$B$5),'Sales Data'!$B$2:$B$1201,"<="&MIN(EOMONTH(A12,0),$B$6)) -> 299213 | D12: =SUMIFS('Sales Data'!$R$2:$R$1201,'Sales Data'!$G$2:$G$1201,$B$3,'Sales Data'!$I$2:$I$1201,$B$4,'Sales Data'!$B$2:$B$1201,">="&MAX(A12,$B$5),'Sales Data'!$B$2:$B$1201,"<="&MIN(EOMONTH(A12,0),$B$6)) -> 54393
A13: =DATE(2025,4,1) -> 45748 | B13: =TEXT(A13,"mmm") -> Apr | C13: =SUMIFS('Sales Data'!$P$2:$P$1201,'Sales Data'!$G$2:$G$1201,$B$3,'Sales Data'!$I$2:$I$1201,$B$4,'Sales Data'!$B$2:$B$1201,">="&MAX(A13,$B$5),'Sales Data'!$B$2:$B$1201,"<="&MIN(EOMONTH(A13,0),$B$6)) -> 424765 | D13: =SUMIFS('Sales Data'!$R$2:$R$1201,'Sales Data'!$G$2:$G$1201,$B$3,'Sales Data'!$I$2:$I$1201,$B$4,'Sales Data'!$B$2:$B$1201,">="&MAX(A13,$B$5),'Sales Data'!$B$2:$B$1201,"<="&MIN(EOMONTH(A13,0),$B$6)) -> 90505
A14: =DATE(2025,5,1) -> 45778 | B14: =TEXT(A14,"mmm") -> May | C14: =SUMIFS('Sales Data'!$P$2:$P$1201,'Sales Data'!$G$2:$G$1201,$B$3,'Sales Data'!$I$2:$I$1201,$B$4,'Sales Data'!$B$2:$B$1201,">="&MAX(A14,$B$5),'Sales Data'!$B$2:$B$1201,"<="&MIN(EOMONTH(A14,0),$B$6)) -> 444324 | D14: =SUMIFS('Sales Data'!$R$2:$R$1201,'Sales Data'!$G$2:$G$1201,$B$3,'Sales Data'!$I$2:$I$1201,$B$4,'Sales Data'!$B$2:$B$1201,">="&MAX(A14,$B$5),'Sales Data'!$B$2:$B$1201,"<="&MIN(EOMONTH(A14,0),$B$6)) -> 89104
A15: =DATE(2025,6,1) -> 45809 | B15: =TEXT(A15,"mmm") -> Jun | C15: =SUMIFS('Sales Data'!$P$2:$P$1201,'Sales Data'!$G$2:$G$1201,$B$3,'Sales Data'!$I$2:$I$1201,$B$4,'Sales Data'!$B$2:$B$1201,">="&MAX(A15,$B$5),'Sales Data'!$B$2:$B$1201,"<="&MIN(EOMONTH(A15,0),$B$6)) -> 498900 | D15: =SUMIFS('Sales Data'!$R$2:$R$1201,'Sales Data'!$G$2:$G$1201,$B$3,'Sales Data'!$I$2:$I$1201,$B$4,'Sales Data'!$B$2:$B$1201,">="&MAX(A15,$B$5),'Sales Data'!$B$2:$B$1201,"<="&MIN(EOMONTH(A15,0),$B$6)) -> 115750
A16: =DATE(2025,7,1) -> 45839 | B16: =TEXT(A16,"mmm") -> Jul | C16: =SUMIFS('Sales Data'!$P$2:$P$1201,'Sales Data'!$G$2:$G$1201,$B$3,'Sales Data'!$I$2:$I$1201,$B$4,'Sales Data'!$B$2:$B$1201,">="&MAX(A16,$B$5),'Sales Data'!$B$2:$B$1201,"<="&MIN(EOMONTH(A16,0),$B$6)) -> 418685 | D16: =SUMIFS('Sales Data'!$R$2:$R$1201,'Sales Data'!$G$2:$G$1201,$B$3,'Sales Data'!$I$2:$I$1201,$B$4,'Sales Data'!$B$2:$B$1201,">="&MAX(A16,$B$5),'Sales Data'!$B$2:$B$1201,"<="&MIN(EOMONTH(A16,0),$B$6)) -> 92285
A17: =DATE(2025,8,1) -> 45870 | B17: =TEXT(A17,"mmm") -> Aug | C17: =SUMIFS('Sales Data'!$P$2:$P$1201,'Sales Data'!$G$2:$G$1201,$B$3,'Sales Data'!$I$2:$I$1201,$B$4,'Sales Data'!$B$2:$B$1201,">="&MAX(A17,$B$5),'Sales Data'!$B$2:$B$1201,"<="&MIN(EOMONTH(A17,0),$B$6)) -> 379426 | D17: =SUMIFS('Sales Data'!$R$2:$R$1201,'Sales Data'!$G$2:$G$1201,$B$3,'Sales Data'!$I$2:$I$1201,$B$4,'Sales Data'!$B$2:$B$1201,">="&MAX(A17,$B$5),'Sales Data'!$B$2:$B$1201,"<="&MIN(EOMONTH(A17,0),$B$6)) -> 90066
A18: =DATE(2025,9,1) -> 45901 | B18: =TEXT(A18,"mmm") -> Sep | C18: =SUMIFS('Sales Data'!$P$2:$P$1201,'Sales Data'!$G$2:$G$1201,$B$3,'Sales Data'!$I$2:$I$1201,$B$4,'Sales Data'!$B$2:$B$1201,">="&MAX(A18,$B$5),'Sales Data'!$B$2:$B$1201,"<="&MIN(EOMONTH(A18,0),$B$6)) -> 366784 | D18: =SUMIFS('Sales Data'!$R$2:$R$1201,'Sales Data'!$G$2:$G$1201,$B$3,'Sales Data'!$I$2:$I$1201,$B$4,'Sales Data'!$B$2:$B$1201,">="&MAX(A18,$B$5),'Sales Data'!$B$2:$B$1201,"<="&MIN(EOMONTH(A18,0),$B$6)) -> 93744
A19: =DATE(2025,10,1) -> 45931 | B19: =TEXT(A19,"mmm") -> Oct | C19: =SUMIFS('Sales Data'!$P$2:$P$1201,'Sales Data'!$G$2:$G$1201,$B$3,'Sales Data'!$I$2:$I$1201,$B$4,'Sales Data'!$B$2:$B$1201,">="&MAX(A19,$B$5),'Sales Data'!$B$2:$B$1201,"<="&MIN(EOMONTH(A19,0),$B$6)) -> 668213 | D19: =SUMIFS('Sales Data'!$R$2:$R$1201,'Sales Data'!$G$2:$G$1201,$B$3,'Sales Data'!$I$2:$I$1201,$B$4,'Sales Data'!$B$2:$B$1201,">="&MAX(A19,$B$5),'Sales Data'!$B$2:$B$1201,"<="&MIN(EOMONTH(A19,0),$B$6)) -> 169513
A20: =DATE(2025,11,1) -> 45962 | B20: =TEXT(A20,"mmm") -> Nov | C20: =SUMIFS('Sales Data'!$P$2:$P$1201,'Sales Data'!$G$2:$G$1201,$B$3,'Sales Data'!$I$2:$I$1201,$B$4,'Sales Data'!$B$2:$B$1201,">="&MAX(A20,$B$5),'Sales Data'!$B$2:$B$1201,"<="&MIN(EOMONTH(A20,0),$B$6)) -> 776952 | D20: =SUMIFS('Sales Data'!$R$2:$R$1201,'Sales Data'!$G$2:$G$1201,$B$3,'Sales Data'!$I$2:$I$1201,$B$4,'Sales Data'!$B$2:$B$1201,">="&MAX(A20,$B$5),'Sales Data'!$B$2:$B$1201,"<="&MIN(EOMONTH(A20,0),$B$6)) -> 176062
A21: =DATE(2025,12,1) -> 45992 | B21: =TEXT(A21,"mmm") -> Dec | C21: =SUMIFS('Sales Data'!$P$2:$P$1201,'Sales Data'!$G$2:$G$1201,$B$3,'Sales Data'!$I$2:$I$1201,$B$4,'Sales Data'!$B$2:$B$1201,">="&MAX(A21,$B$5),'Sales Data'!$B$2:$B$1201,"<="&MIN(EOMONTH(A21,0),$B$6)) -> 533194 | D21: =SUMIFS('Sales Data'!$R$2:$R$1201,'Sales Data'!$G$2:$G$1201,$B$3,'Sales Data'!$I$2:$I$1201,$B$4,'Sales Data'!$B$2:$B$1201,">="&MAX(A21,$B$5),'Sales Data'!$B$2:$B$1201,"<="&MIN(EOMONTH(A21,0),$B$6)) -> 115004
A24: Region | B24: Sales (₹)
A25: East | B25: =SUMIFS('Sales Data'!$P$2:$P$1201,'Sales Data'!$G$2:$G$1201,A25,'Sales Data'!$G$2:$G$1201,$B$3,'Sales Data'!$I$2:$I$1201,$B$4,'Sales Data'!$B$2:$B$1201,">="&$B$5,'Sales Data'!$B$2:$B$1201,"<="&$B$6) -> 333766
A26: North | B26: =SUMIFS('Sales Data'!$P$2:$P$1201,'Sales Data'!$G$2:$G$1201,A26,'Sales Data'!$G$2:$G$1201,$B$3,'Sales Data'!$I$2:$I$1201,$B$4,'Sales Data'!$B$2:$B$1201,">="&$B$5,'Sales Data'!$B$2:$B$1201,"<="&$B$6) -> 1155087
A27: South | B27: =SUMIFS('Sales Data'!$P$2:$P$1201,'Sales Data'!$G$2:$G$1201,A27,'Sales Data'!$G$2:$G$1201,$B$3,'Sales Data'!$I$2:$I$1201,$B$4,'Sales Data'!$B$2:$B$1201,">="&$B$5,'Sales Data'!$B$2:$B$1201,"<="&$B$6) -> 1747516
A28: West | B28: =SUMIFS('Sales Data'!$P$2:$P$1201,'Sales Data'!$G$2:$G$1201,A28,'Sales Data'!$G$2:$G$1201,$B$3,'Sales Data'!$I$2:$I$1201,$B$4,'Sales Data'!$B$2:$B$1201,">="&$B$5,'Sales Data'!$B$2:$B$1201,"<="&$B$6) -> 2190302
A31: Category | B31: Profit (₹)
A32: Apparel | B32: =SUMIFS('Sales Data'!$R$2:$R$1201,'Sales Data'!$I$2:$I$1201,A32,'Sales Data'!$I$2:$I$1201,$B$4,'Sales Data'!$G$2:$G$1201,$B$3,'Sales Data'!$B$2:$B$1201,">="&$B$5,'Sales Data'!$B$2:$B$1201,"<="&$B$6) -> 200041
A33: Beauty | B33: =SUMIFS('Sales Data'!$R$2:$R$1201,'Sales Data'!$I$2:$I$1201,A33,'Sales Data'!$I$2:$I$1201,$B$4,'Sales Data'!$G$2:$G$1201,$B$3,'Sales Data'!$B$2:$B$1201,">="&$B$5,'Sales Data'!$B$2:$B$1201,"<="&$B$6) -> 154704
A34: Electronics | B34: =SUMIFS('Sales Data'!$R$2:$R$1201,'Sales Data'!$I$2:$I$1201,A34,'Sales Data'!$I$2:$I$1201,$B$4,'Sales Data'!$G$2:$G$1201,$B$3,'Sales Data'!$B$2:$B$1201,">="&$B$5,'Sales Data'!$B$2:$B$1201,"<="&$B$6) -> 447735
A35: Furniture | B35: =SUMIFS('Sales Data'!$R$2:$R$1201,'Sales Data'!$I$2:$I$1201,A35,'Sales Data'!$I$2:$I$1201,$B$4,'Sales Data'!$G$2:$G$1201,$B$3,'Sales Data'!$B$2:$B$1201,">="&$B$5,'Sales Data'!$B$2:$B$1201,"<="&$B$6) -> 56785
A36: Home | B36: =SUMIFS('Sales Data'!$R$2:$R$1201,'Sales Data'!$I$2:$I$1201,A36,'Sales Data'!$I$2:$I$1201,$B$4,'Sales Data'!$G$2:$G$1201,$B$3,'Sales Data'!$B$2:$B$1201,">="&$B$5,'Sales Data'!$B$2:$B$1201,"<="&$B$6) -> 256160
A37: Stationery | B37: =SUMIFS('Sales Data'!$R$2:$R$1201,'Sales Data'!$I$2:$I$1201,A37,'Sales Data'!$I$2:$I$1201,$B$4,'Sales Data'!$G$2:$G$1201,$B$3,'Sales Data'!$B$2:$B$1201,">="&$B$5,'Sales Data'!$B$2:$B$1201,"<="&$B$6) -> 97016
A40: Discount Band | B40: Orders | C40: Sales (₹) | D40: Profit (₹) | E40: Margin
A41: No discount | B41: =COUNTIFS('Sales Data'!$T$2:$T$1201,A41,'Sales Data'!$G$2:$G$1201,$B$3,'Sales Data'!$I$2:$I$1201,$B$4,'Sales Data'!$B$2:$B$1201,">="&$B$5,'Sales Data'!$B$2:$B$1201,"<="&$B$6) -> 367 | C41: =SUMIFS('Sales Data'!$P$2:$P$1201,'Sales Data'!$T$2:$T$1201,A41,'Sales Data'!$G$2:$G$1201,$B$3,'Sales Data'!$I$2:$I$1201,$B$4,'Sales Data'!$B$2:$B$1201,">="&$B$5,'Sales Data'!$B$2:$B$1201,"<="&$B$6) -> 1494101 | D41: =SUMIFS('Sales Data'!$R$2:$R$1201,'Sales Data'!$T$2:$T$1201,A41,'Sales Data'!$G$2:$G$1201,$B$3,'Sales Data'!$I$2:$I$1201,$B$4,'Sales Data'!$B$2:$B$1201,">="&$B$5,'Sales Data'!$B$2:$B$1201,"<="&$B$6) -> 541151 | E41: =IF(C41=0,0,D41/C41) -> 0.36219171
A42: Up to 20% | B42: =COUNTIFS('Sales Data'!$T$2:$T$1201,A42,'Sales Data'!$G$2:$G$1201,$B$3,'Sales Data'!$I$2:$I$1201,$B$4,'Sales Data'!$B$2:$B$1201,">="&$B$5,'Sales Data'!$B$2:$B$1201,"<="&$B$6) -> 643 | C42: =SUMIFS('Sales Data'!$P$2:$P$1201,'Sales Data'!$T$2:$T$1201,A42,'Sales Data'!$G$2:$G$1201,$B$3,'Sales Data'!$I$2:$I$1201,$B$4,'Sales Data'!$B$2:$B$1201,">="&$B$5,'Sales Data'!$B$2:$B$1201,"<="&$B$6) -> 3062479 | D42: =SUMIFS('Sales Data'!$R$2:$R$1201,'Sales Data'!$T$2:$T$1201,A42,'Sales Data'!$G$2:$G$1201,$B$3,'Sales Data'!$I$2:$I$1201,$B$4,'Sales Data'!$B$2:$B$1201,">="&$B$5,'Sales Data'!$B$2:$B$1201,"<="&$B$6) -> 718399 | E42: =IF(C42=0,0,D42/C42) -> 0.23458087
A43: Above 20% | B43: =COUNTIFS('Sales Data'!$T$2:$T$1201,A43,'Sales Data'!$G$2:$G$1201,$B$3,'Sales Data'!$I$2:$I$1201,$B$4,'Sales Data'!$B$2:$B$1201,">="&$B$5,'Sales Data'!$B$2:$B$1201,"<="&$B$6) -> 190 | C43: =SUMIFS('Sales Data'!$P$2:$P$1201,'Sales Data'!$T$2:$T$1201,A43,'Sales Data'!$G$2:$G$1201,$B$3,'Sales Data'!$I$2:$I$1201,$B$4,'Sales Data'!$B$2:$B$1201,">="&$B$5,'Sales Data'!$B$2:$B$1201,"<="&$B$6) -> 870091 | D43: =SUMIFS('Sales Data'!$R$2:$R$1201,'Sales Data'!$T$2:$T$1201,A43,'Sales Data'!$G$2:$G$1201,$B$3,'Sales Data'!$I$2:$I$1201,$B$4,'Sales Data'!$B$2:$B$1201,">="&$B$5,'Sales Data'!$B$2:$B$1201,"<="&$B$6) -> -47109 | E43: =IF(C43=0,0,D43/C43) -> -0.054142613
A46: KPI | B46: Value
A47: Sales (₹) | B47: =SUMIFS('Sales Data'!$P$2:$P$1201,'Sales Data'!$G$2:$G$1201,$B$3,'Sales Data'!$I$2:$I$1201,$B$4,'Sales Data'!$B$2:$B$1201,">="&$B$5,'Sales Data'!$B$2:$B$1201,"<="&$B$6) -> 5426671
A48: Profit (₹) | B48: =SUMIFS('Sales Data'!$R$2:$R$1201,'Sales Data'!$G$2:$G$1201,$B$3,'Sales Data'!$I$2:$I$1201,$B$4,'Sales Data'!$B$2:$B$1201,">="&$B$5,'Sales Data'!$B$2:$B$1201,"<="&$B$6) -> 1212441
A49: Profit margin | B49: =IF(B47=0,0,B48/B47) -> 0.22342261
A50: Orders | B50: =COUNTIFS('Sales Data'!$G$2:$G$1201,$B$3,'Sales Data'!$I$2:$I$1201,$B$4,'Sales Data'!$B$2:$B$1201,">="&$B$5,'Sales Data'!$B$2:$B$1201,"<="&$B$6) -> 1200
A51: Average order value (₹) | B51: =IF(B50=0,0,B47/B50) -> 4522.2258
A52: Share of full-year sales | B52: =B47/SUM('Sales Data'!$P$2:$P$1201) -> 1
A53: Share of full-year profit | B53: =B48/SUM('Sales Data'!$R$2:$R$1201) -> 1
A54: Full-year margin | B54: =SUM('Sales Data'!$R$2:$R$1201)/SUM('Sales Data'!$P$2:$P$1201) -> 0.22342261
